Workbook

Sheet Cover
C3: Nestlé India Comparable Valuation
C8: Relative Value Estimate using Comparable Company & Precedent Transaction Analysis
C11: Table of Contents | N11: Model Information
C13: Select a worksheet below to navigate. | N13: Prepared by | O13: : | P13: Mohd Talib Raeen
C14: Inputs
N15: Company | O15: : | P15: Nestlé India Limited
C16: Trading Comps
N17: Date | O17: : | P17: 46174
C18: Precedent Transactions
N19: Currency | O19: : | P19: All amounts in ₹ crores,
C20: Appendix | P20: unless otherwise stated
N21: Valuation | O21: : | P21: Comparable Company Analysis &
P22: Precedent Transaction Analysis
C27: Confidentiality Note: | N27: Navigation Tip:
C28: This comparable valuation model has been prepared for educational and interview purposes only. | N28: Use Ctrl + ↑ / Ctrl + ↓ in Column A to jump
C29: It is intended solely for the designated recipient and should not be distributed, reproduced, modified, | N29: between section markers within worksheets.
C30: or used for commercial or investment purposes without prior permission.

Sheet Inputs
B2: Calculation of Enterprise Value
B3: Peers | D3: Market Cap | E3: Borrowing | F3: Lease Liabilities | G3: NCI | H3: CCE | I3: Current Investment ¹ | J3: Non Current Investment ¹ | K3: Enterprise Value
B5: Hindustan Unilever Ltd | D5: =2055.2*(2349591262/10000000) -> 482888 | E5: 0 | F5: =1104+374 -> 1478 | G5: 269 | H5: =(2583+665)*-1 -> -3248 | I5: -4247 | J5: -112 | K5: =SUM(D5:J5) -> 477028
B6: ITC Ltd | D6: =287.7*1252.95 -> 360473.72 | E6: =60+2126.22 -> 2186.22 | F6: =140.86+71.98 -> 212.84 | G6: 365.72 | H6: =(643.46+2365.33)*-1 -> -3008.79 | I6: -20750.64 | J6: -12089.55 | K6: =SUM(D6:J6) -> 327389.52
B7: Dabur India Ltd | D7: =410.45*177.23 -> 72744.053 | E7: =15.96+1046.72 -> 1062.68 | F7: =181.18+43.46 -> 224.64 | G7: 383.23 | H7: =(199.37+362.7)*-1 -> -562.07 | I7: -4595.47 | J7: -4331.16 | K7: =SUM(D7:J7) -> 64925.903
B8: Tata Consumer Products Ltd | D8: =1014.8*(989561780/10000000) -> 100420.73 | E8: =302.14+1818.17 -> 2120.31 | F8: =608.64+90.56 -> 699.2 | G8: 1401.33 | H8: =(3046.57+373.92)*-1 -> -3420.49 | I8: -868.2 | J8: -285.7 | K8: =SUM(D8:J8) -> 100067.18
B10: Calculation of EBITDA
B11: Peers | D11: Profit before share of loss, exceptional items and tax | E11: Finance Cost | F11: Depreciation & Ammortization | G11: EBITDA | H11: Revenue 2026A | I11: EBITDA Margin | J11: Revenue 2027F ² | K11: EBITDA 2027F
B13: Nestle India Ltd | D13: 44888.7 | E13: 1583.1 | F13: 6992.3 | G13: =SUM(D13:F13) -> 53464.1 | H13: 231546 | I13: - | J13: - | K13: -
B14: Hindustan Unilever Ltd | D14: 14062 | E14: 410 | F14: 1333 | G14: =SUM(D14:F14) -> 15805 | H14: 64468 | I14: =G14/H14 -> 0.24516039 | J14: =H14*(1+0.12) -> 72204.16 | K14: =J14*I14 -> 17701.6
B15: ITC Ltd | D15: =28325.09-377.08 -> 27948.01 | E15: 85.17 | F15: 1710.53 | G15: =SUM(D15:F15) -> 29743.71 | H15: 89913.33 | I15: =G15/H15 -> 0.33080423 | J15: =H15*(1+0.042) -> 93689.69 | K15: =J15*I15 -> 30992.946
B16: Dabur India Ltd | D16: 2437.28 | E16: 145.4 | F16: 468.93 | G16: =SUM(D16:F16) -> 3051.61 | H16: 13192.57 | I16: =G16/H16 -> 0.23131278 | J16: =H16*(1+0.05) -> 13852.199 | K16: =J16*I16 -> 3204.1905
B17: Tata Consumer Products Ltd | D17: 2192.84 | E17: 137.03 | F17: 626.68 | G17: =SUM(D17:F17) -> 2956.55 | H17: 20290.43 | I17: =G17/H17 -> 0.14571155 | J17: =H17*(1+0.123) -> 22786.153 | K17: =J17*I17 -> 3320.2057
B19: Calculation of Net Income
B20: Peers | D20: Net Profit | H20: Growth | K20: Average Growth
B22: Hindustan Unilever Ltd | D22: 10143 | E22: 10282 | F22: 10671 | G22: 15059 | H22: =(E22-D22)/E22 -> 0.013518771 | I22: =(F22-E22)/F22 -> 0.036453941 | J22: =(G22-F22)/G22 -> 0.29138721 | K22: =AVERAGE(H22:J22)/3 -> 0.03792888
B23: ITC Ltd | D23: 19477 | E23: 20751 | F23: 35052 | G23: 21018 | H23: =(E23-D23)/E23 -> 0.061394632 | I23: =(F23-E23)/F23 -> 0.40799384 | J23: =(G23-F23)/G23 -> -0.66771339 | K23: =AVERAGE(H23:J23)/3 -> -0.022036102
B24: Dabur India Ltd | D24: 1701 | E24: 1811 | F24: 1740 | G24: 1869 | H24: =(E24-D24)/E24 -> 0.060739923 | I24: =(F24-E24)/F24 -> -0.040804598 | J24: =(G24-F24)/G24 -> 0.069020867 | K24: =AVERAGE(H24:J24)/3 -> 0.0098840213
B25: Tata Consumer Products Ltd | D25: 1320 | E25: 1215 | F25: 1287 | G25: 1547 | H25: =(E25-D25)/E25 -> -0.086419753 | I25: =(F25-E25)/F25 -> 0.055944056 | J25: =(G25-F25)/G25 -> 0.16806723 | K25: =AVERAGE(H25:J25)/3 -> 0.015287948

Sheet Trading Comps
B2: Comparable Trading Analysis
B4: Peer Companies | C4: Enterprise | D4: Market | E4: EBITDA | G4: Net Income | I4: EV / EBITDA | K4: P / E
C5: Value | D5: Cap | E5: 2026 | F5: 2027 | G5: 2026 | H5: 2027 | I5: 2026 | J5: 2027 | K5: 2026 | L5: 2027
B7: Hindustan Unilever Ltd | C7: =Inputs!K5 -> 477028 | D7: =Inputs!D5 -> 482888 | E7: =Inputs!G14 -> 15805 | F7: =Inputs!K14 -> 17701.6 | G7: 15059 | H7: =G7*(1+Inputs!K22) -> 15630.171 | I7: =C7/E7 -> 30.182094 | J7: =C7/F7 -> 26.948298 | K7: =D7/G7 -> 32.066405 | L7: =D7/H7 -> 30.894607
B8: ITC Ltd | C8: =Inputs!K6 -> 327389.52 | D8: =Inputs!D6 -> 360473.72 | E8: =Inputs!G15 -> 29743.71 | F8: =Inputs!K15 -> 30992.946 | G8: 21018.15 | H8: =G8*(1+Inputs!K23) -> 20554.992 | I8: =C8/E8 -> 11.007017 | J8: =C8/F8 -> 10.563356 | K8: =D8/G8 -> 17.150592 | L8: =D8/H8 -> 17.53704
B9: Dabur India Ltd | C9: =Inputs!K7 -> 64925.903 | D9: =Inputs!D7 -> 72744.053 | E9: =Inputs!G16 -> 3051.61 | F9: =Inputs!K16 -> 3204.1905 | G9: 1868.69 | H9: =G9*(1+Inputs!K24) -> 1887.1602 | I9: =C9/E9 -> 21.275951 | J9: =C9/F9 -> 20.26281 | K9: =D9/G9 -> 38.927834 | L9: =D9/H9 -> 38.546836
B10: Tata Consumer Products Ltd | C10: =Inputs!K8 -> 100067.18 | D10: =Inputs!D8 -> 100420.73 | E10: =Inputs!G17 -> 2956.55 | F10: =Inputs!K17 -> 3320.2057 | G10: 1546.8 | H10: =G10*(1+Inputs!K25) -> 1570.4474 | I10: =C10/E10 -> 33.845928 | J10: =C10/F10 -> 30.13885 | K10: =D10/G10 -> 64.921599 | L10: =D10/H10 -> 63.944026
B13: Nestlé India Valuation
B15: Average | C15: =E15*I15 -> 1287295.1 | D15: =G15*K15 -> 1338979.2 | E15: =Inputs!G13 -> 53464.1 | G15: 34990.8 | I15: =AVERAGE(I7:I10) -> 24.077747 | J15: =AVERAGE(J7:J10) -> 21.978328 | K15: =AVERAGE(K7:K10) -> 38.266607 | L15: =AVERAGE(L7:L10) -> 37.730627
B16: Median | C16: =E16*I16 -> 1375579 | D16: =G16*K16 -> 1242072.6 | E16: =E15 -> 53464.1 | G16: =G15 -> 34990.8 | I16: =MEDIAN(I7:I10) -> 25.729022 | J16: =MEDIAN(J7:J10) -> 23.605554 | K16: =MEDIAN(K7:K10) -> 35.497119 | L16: =MEDIAN(L7:L10) -> 34.720722
B17: Maximum | C17: =E17*I17 -> 1809542.1 | D17: =G17*K17 -> 2271658.7 | E17: =E16 -> 53464.1 | G17: =G16 -> 34990.8 | I17: =MAX(I7:I10) -> 33.845928 | J17: =MAX(J7:J10) -> 30.13885 | K17: =MAX(K7:K10) -> 64.921599 | L17: =MAX(L7:L10) -> 63.944026
B18: Minimum | C18: =E18*I18 -> 588480.25 | D18: =G18*K18 -> 600112.93 | E18: =E17 -> 53464.1 | G18: =G17 -> 34990.8 | I18: =MIN(I7:I10) -> 11.007017 | J18: =MIN(J7:J10) -> 10.563356 | K18: =MIN(K7:K10) -> 17.150592 | L18: =MIN(L7:L10) -> 17.53704

Sheet Precedent Transactions
B2: Precedent Transaction Analysis
B4: Date | C4: Acquirer | D4: Target | E4: Enterprise | F4: Revenue | G4: EV / Revenue
E5: Value | F5: 2026 | G5: 2026
B7: 45694 | C7: ITC Ltd | D7: Prasuma ³ | E7: 300 | F7: =200/3*12 -> 800 | G7: =$E7/F7 -> 0.375
B8: 45764 | C8: ITC Ltd | D8: Sresta Natural Bioproducts Pvt. Ltd | E8: 472.5 | F8: 306 | G8: =$E8/F8 -> 1.5441176
B9: 44860 | C9: Dabur India Ltd | D9: Badshah Masala Pvt. Ltd | E9: 1152 | F9: =E9/4.5 -> 256 | G9: =$E9/F9 -> 4.5
B10: 45303 | C10: Tata Consumer Products Ltd | D10: Capital Foods Pvt. Ltd | E10: 5100 | F10: 705.5 | G10: =$E10/F10 -> 7.2289157
B11: 45334 | C11: Tata Consumer Products Ltd | D11: Organic India Pvt. Ltd | E11: 1900 | F11: 324.4 | G11: =$E11/F11 -> 5.8569667
B12: 45781 | C12: AWL Agri Business Ltd | D12: G.D. Foods Manufacturing Pvt. Ltd | E12: 603 | F12: 386 | G12: =$E12/F12 -> 1.5621762
B15: Nestlé India Valuation
B17: Average | E17: =F17*G17 -> 813003.4 | F17: =Inputs!H13 -> 231546 | G17: =AVERAGE(G7:G12) -> 3.511196
B18: Median | E18: =F18*G18 -> 701836.32 | F18: =F17 -> 231546 | G18: =MEDIAN(G7:G12) -> 3.0310881
B19: Maximum | E19: =F19*G19 -> 1673826.5 | F19: =F18 -> 231546 | G19: =MAX(G7:G12) -> 7.2289157
B20: Minimum | E20: =F20*G20 -> 86829.75 | F20: =F19 -> 231546 | G20: =MIN(G7:G12) -> 0.375

Sheet Appendix
B2: Ref. No | C2: Note
B3: 1 | C3: EV bridge uses consolidated balance sheet book values. Cash and cash equivalents,
C4: bank balances, and financial investments are deducted as non-operating liquid assets.
C5: No further note-level split is made between operating and non-operating investments;
C6: this is a simplifying assumption applied consistently across all companies.
B7: 2 | C7: Revenue Growth:
C8: Hindustan Unilever Ltd | D8: 0.123
C9: ITC Ltd | D9: 0.042
C10: Dabur India Ltd | D10: 0.05
C11: Tata Consumer Products Ltd | D11: 0.123
B12: 3 | C12: Revenue and EBITDA based on latest available financial information. Partial-year results
C13: annualized where appropriate.

Sheet Rough
B2: Line item | C2: 2027F rule
B3: Revenue | C3: FY26A Revenue × 1.05
B4: EBITDA | C4: Revenue × FY26A EBITDA margin, or Revenue × 1 slightly adjusted margin
B5: EBIT | C5: EBITDA - D&A, with D&A as % of revenue or flat vs FY26A
B6: Net income | C6: FY26A PAT × 1.03 to 1.05, unless you model tax / other income separately
