Workbook

Sheet Cover
C3: Hindustan Unilever DCF Valuation
C8: Intrinsic Value Estimate using DCF Method
C11: Table of Contents | N11: Model Information
C13: Select a worksheet below to navigate. | N13: Prepared by | O13: : | P13: Mohd Talib Raeen
C14: Dashboard
N15: Company | O15: : | P15: Hindustan Unilever Limited
C16: Assumption
N17: Date | O17: : | P17: 46174
C18: Core_Model
N19: Currency | O19: : | P19: All amounts in ₹ crores,
C20: Schedules | P20: unless otherwise stated
N21: Scenarios | O21: : | P21: Base / Bull / Bear
C22: Valuation_DCF
C24: Sensitivity_Analysis | N24: Navigation Tip:
N25: Use Ctrl + ↑ / Ctrl + ↓ in Column A to jump
C26: Appendix | N26: between section markers within worksheets.
C30: Confidentiality Note:
C31: This financial model is prepared for educational and interview purposes only.
C32: It is intended solely for the recipient and should not be distributed, reproduced, or used without permission

Sheet Dashboard
B2: Profit Margin | J2: Expenses | S2: Driver Switch
S4: =Assumptions!B2 -> Particulars | T4: =Assumptions!H2 -> 2026 | U4: =Assumptions!I2 -> 2027 | V4: =Assumptions!J2 -> 2028 | W4: =Assumptions!K2 -> 2029 | X4: =Assumptions!L2 -> 2030
S6: Revenue | T6: =Core_Model!H5 -> 66277.05 | U6: =Core_Model!I5 -> 71711.768 | V6: =Core_Model!J5 -> 77448.71 | W6: =Core_Model!K5 -> 82870.119 | X6: =Core_Model!L5 -> 87842.326
S7: EBITDA | T7: 15813.164 | U7: 18448.118 | V7: 21433.295 | W7: 24337.747 | X7: 27241.418
S8: Net Income | T8: 10803.821 | U8: 12808.608 | V8: 15053.86 | W8: 17211.093 | X8: 19342.581
S10: EBITDA Margin % | T10: =T7/T6 -> 0.23859185 | U10: =U7/U6 -> 0.25725371 | V10: =V7/V6 -> 0.2767418 | W10: =W7/W6 -> 0.29368544 | X10: =X7/X6 -> 0.31011722
S11: ROCE | T11: =Core_Model!H14/(Core_Model!H60+Core_Model!H61+Core_Model!H55) -> 0.28105557 | U11: =Core_Model!I14/(Core_Model!I60+Core_Model!I61+Core_Model!I55) -> 0.30150208 | V11: =Core_Model!J14/(Core_Model!J60+Core_Model!J61+Core_Model!J55) -> 0.32682754 | W11: =Core_Model!K14/(Core_Model!K60+Core_Model!K61+Core_Model!K55) -> 0.34997596 | X11: =Core_Model!L14/(Core_Model!L60+Core_Model!L61+Core_Model!L55) -> 0.36865411
S12: ROE | T12: =Core_Model!H25/(Core_Model!H60+Core_Model!H61) -> 0.21462844 | U12: =Core_Model!I25/(Core_Model!I60+Core_Model!I61) -> 0.23201197 | V12: =Core_Model!J25/(Core_Model!J60+Core_Model!J61) -> 0.25280453 | W12: =Core_Model!K25/(Core_Model!K60+Core_Model!K61) -> 0.27156202 | X12: =Core_Model!L25/(Core_Model!L60+Core_Model!L61) -> 0.28662038
S15: Expenses
S16: COGS | T16: =Core_Model!H6*-1 -> 32045.744 | U16: =Core_Model!I6*-1 -> 34769.632 | V16: =Core_Model!J6*-1 -> 37412.124 | W16: =Core_Model!K6*-1 -> 39843.912 | X16: =Core_Model!L6*-1 -> 42035.328
S17: SG&A | T17: =Core_Model!H9*-1 -> 3218.542 | U17: =Core_Model!I9*-1 -> 3366.5949 | V17: =Core_Model!J9*-1 -> 3521.4583 | W17: =Core_Model!K9*-1 -> 3683.4454 | X17: =Core_Model!L9*-1 -> 3852.8839
S18: Other Operating Expenses | T18: =Core_Model!H10*-1 -> 15199.6 | U18: =Core_Model!I10*-1 -> 16339.57 | V18: =Core_Model!J10*-1 -> 17516.019 | W18: =Core_Model!K10*-1 -> 18602.012 | X18: =Core_Model!L10*-1 -> 19625.123
B19: Capital Return Efficiency | J19: Cash Flows | S19: Depreciation | T19: =Core_Model!H13*-1 -> 1354.0031 | U19: =Core_Model!I13*-1 -> 1456.1106 | V19: =Core_Model!J13*-1 -> 1566.591 | W19: =Core_Model!K13*-1 -> 1685.9097 | X19: =Core_Model!L13*-1 -> 1813.5807
S20: Other Income | T20: =Core_Model!H16 -> 994.15575 | U20: =Core_Model!I16 -> 1075.6765 | V20: =Core_Model!J16 -> 1161.7306 | W20: =Core_Model!K16 -> 1243.0518 | X20: =Core_Model!L16 -> 1317.6349
S21: Total Expense | T21: =SUM(T16:T20) -> 52812.045 | U21: =SUM(U16:U20) -> 57007.584 | V21: =SUM(V16:V20) -> 61177.923 | W21: =SUM(W16:W20) -> 65058.331 | X21: =SUM(X16:X20) -> 68644.55
S24: Cash Flow
S25: Cash From Operations | T25: =Core_Model!H81 -> 10024.671 | U25: =Core_Model!I81 -> 14136.032 | V25: =Core_Model!J81 -> 15674.519 | W25: =Core_Model!K81 -> 16909.561 | X25: =Core_Model!L81 -> 18131.783
S26: Cash From Investing | T26: =Core_Model!H87 -> -1458.0951 | U26: =Core_Model!I87 -> -1577.6589 | V26: =Core_Model!J87 -> -1703.8716 | W26: =Core_Model!K87 -> -1823.1426 | X26: =Core_Model!L87 -> -1932.5312
S27: Cash From Financing | T27: =Core_Model!H96 -> -9987.3974 | U27: =Core_Model!I96 -> -10991.08 | V27: =Core_Model!J96 -> -12213.721 | W27: =Core_Model!K96 -> -13403.006 | X27: =Core_Model!L96 -> -14471.256
S28: Cash Balance | T28: =Core_Model!H102 -> 4685.1783 | U28: =Core_Model!I102 -> 6252.4707 | V28: =Core_Model!J102 -> 8009.3964 | W28: =Core_Model!K102 -> 9692.8083 | X28: =Core_Model!L102 -> 11420.804

Sheet Assumptions
B2: Particulars | E2: 2023 | F2: 2024 | G2: 2025 | H2: 2026 | I2: 2027 | J2: 2028 | K2: 2029 | L2: 2030
B4: Drivers
B6: Driver Switch | C6: 2
B8: Revenue Growth | H8: {=INDEX(H9:H11,$C$6)} -> 0.05 | I8: {=INDEX(I9:I11,$C$6)} -> 0.082 | J8: {=INDEX(J9:J11,$C$6)} -> 0.08 | K8: {=INDEX(K9:K11,$C$6)} -> 0.07 | L8: {=INDEX(L9:L11,$C$6)} -> 0.06
B9: Bull Case | H9: 0.05 | I9: 0.105 | J9: 0.1 | K9: 0.085 | L9: 0.075
B10: Base Case | H10: 0.05 | I10: 0.082 | J10: 0.08 | K10: 0.07 | L10: 0.06
B11: Bear Case | H11: 0.05 | I11: 0.045 | J11: 0.04 | K11: 0.045 | L11: 0.05
B13: COGS % | H13: {=INDEX(H14:H16,$C$6)} -> 0.048 | I13: {=INDEX(I14:I16,$C$6)} -> 0.085 | J13: {=INDEX(J14:J16,$C$6)} -> 0.076 | K13: {=INDEX(K14:K16,$C$6)} -> 0.065 | L13: {=INDEX(L14:L16,$C$6)} -> 0.055
B14: =B9 -> Bull Case | H14: 0.048 | I14: 0.09 | J14: 0.082 | K14: 0.068 | L14: 0.058
B15: =B10 -> Base Case | H15: 0.048 | I15: 0.085 | J15: 0.076 | K15: 0.065 | L15: 0.055
B16: =B11 -> Bear Case | H16: 0.048 | I16: 0.06 | J16: 0.052 | K16: 0.05 | L16: 0.052
B18: Other Operating Expenses | H18: {=INDEX(H19:H21,$C$6)} -> 0.04 | I18: {=INDEX(I19:I21,$C$6)} -> 0.075 | J18: {=INDEX(J19:J21,$C$6)} -> 0.072 | K18: {=INDEX(K19:K21,$C$6)} -> 0.062 | L18: {=INDEX(L19:L21,$C$6)} -> 0.055
B19: =B14 -> Bull Case | H19: 0.04 | I19: 0.085 | J19: 0.08 | K19: 0.068 | L19: 0.06
B20: =B15 -> Base Case | H20: 0.04 | I20: 0.075 | J20: 0.072 | K20: 0.062 | L20: 0.055
B21: =B16 -> Bear Case | H21: 0.04 | I21: 0.06 | J21: 0.055 | K21: 0.055 | L21: 0.058
B23: Accounts Receivable Days | H23: {=INDEX(H24:H26,$C$6)} -> 21 | I23: {=INDEX(I24:I26,$C$6)} -> 21 | J23: {=INDEX(J24:J26,$C$6)} -> 21 | K23: {=INDEX(K24:K26,$C$6)} -> 21 | L23: {=INDEX(L24:L26,$C$6)} -> 21
B24: =B19 -> Bull Case | H24: 21 | I24: 19.5 | J24: 18.5 | K24: 17.5 | L24: 17
B25: =B20 -> Base Case | H25: 21 | I25: 21 | J25: 21 | K25: 21 | L25: 21
B26: =B21 -> Bear Case | H26: 21 | I26: 23 | J26: 24.5 | K26: 25 | L26: 25
B28: Inventory Days | H28: {=INDEX(H29:H31,$C$6)} -> 51.5 | I28: {=INDEX(I29:I31,$C$6)} -> 51.5 | J28: {=INDEX(J29:J31,$C$6)} -> 51 | K28: {=INDEX(K29:K31,$C$6)} -> 51 | L28: {=INDEX(L29:L31,$C$6)} -> 51
B29: =B24 -> Bull Case | H29: 51.5 | I29: 49 | J29: 48 | K29: 47 | L29: 46.5
B30: =B25 -> Base Case | H30: 51.5 | I30: 51.5 | J30: 51 | K30: 51 | L30: 51
B31: =B26 -> Bear Case | H31: 51.5 | I31: 54 | J31: 55.5 | K31: 56 | L31: 56.5
B33: Accounts Payable Days | H33: {=INDEX(H34:H36,$C$6)} -> 133 | I33: {=INDEX(I34:I36,$C$6)} -> 133 | J33: {=INDEX(J34:J36,$C$6)} -> 134 | K33: {=INDEX(K34:K36,$C$6)} -> 134 | L33: {=INDEX(L34:L36,$C$6)} -> 134
B34: =B29 -> Bull Case | H34: 133 | I34: 135 | J34: 136.5 | K34: 138 | L34: 138.5
B35: =B30 -> Base Case | H35: 133 | I35: 133 | J35: 134 | K35: 134 | L35: 134
B36: =B31 -> Bear Case | H36: 133 | I36: 125 | J36: 120 | K36: 118 | L36: 115
B38: Capex ⁴ | H38: {=INDEX(H39:H41,$C$6)} -> 1458.0951 | I38: {=INDEX(I39:I41,$C$6)} -> 1577.6589 | J38: {=INDEX(J39:J41,$C$6)} -> 1703.8716 | K38: {=INDEX(K39:K41,$C$6)} -> 1823.1426 | L38: {=INDEX(L39:L41,$C$6)} -> 1932.5312
B39: =B34 -> Bull Case | H39: =Core_Model!H5*0.028 -> 1855.7574 | I39: =Core_Model!I5*0.028 -> 2007.9295 | J39: =Core_Model!J5*0.028 -> 2168.5639 | K39: =Core_Model!K5*0.028 -> 2320.3633 | L39: =Core_Model!L5*0.028 -> 2459.5851
B40: =B35 -> Base Case | H40: =Core_Model!H5*0.022 -> 1458.0951 | I40: =Core_Model!I5*0.022 -> 1577.6589 | J40: =Core_Model!J5*0.022 -> 1703.8716 | K40: =Core_Model!K5*0.022 -> 1823.1426 | L40: =Core_Model!L5*0.022 -> 1932.5312
B41: =B36 -> Bear Case | H41: =Core_Model!H5*0.018 -> 1192.9869 | I41: =Core_Model!I5*0.018 -> 1290.8118 | J41: =Core_Model!J5*0.018 -> 1394.0768 | K41: =Core_Model!K5*0.018 -> 1491.6621 | L41: =Core_Model!L5*0.018 -> 1581.1619
B43: WACC | H43: {=INDEX(H44:H46,$C$6)} -> 0.11
B44: =B39 -> Bull Case | H44: 0.1
B45: =B40 -> Base Case | H45: 0.11
B46: =B41 -> Bear Case | H46: 0.12
B48: Other Annual Inputs
B49: Days in Period | E49: 365 | F49: 365 | G49: 365 | H49: 365 | I49: 365 | J49: 366 | K49: 365 | L49: 365
B50: Inflation Rate ¹ | H50: 0.046 | I50: 0.046 | J50: 0.046 | K50: 0.046 | L50: 0.046
B51: Long Term Debt | C51: Increase / (Decrease) | H51: 0 | I51: 0 | J51: 0 | K51: 0 | L51: 0
B52: Common Equity | C52: Increase / (Decrease) | H52: 0 | I52: 0 | J52: 0 | K52: 0 | L52: 0
B53: Tax Rate | H53: 0.26 | I53: 0.26 | J53: 0.26 | K53: 0.26 | L53: 0.26
B54: Dividend Payout Ratio | H54: 0.92 | I54: 0.92 | J54: 0.92 | K54: 0.92 | L54: 0.92
B55: RCL Interest Rate | H55: 0.05 | I55: 0.05 | J55: 0.05 | K55: 0.05 | L55: 0.05
B56: Long Term Debt Interest Rate | H56: 0.05 | I56: 0.05 | J56: 0.05 | K56: 0.05 | L56: 0.05
B57: Shares Outstanding | H57: =2349591262/10000000 -> 234.95913
B58: Valuation Date | H58: =TODAY() -> 46201
B59: First Fiscal Year End for Forecast | H59: 46387
B60: First Expected Cash Flow | H60: 46203
B61: Terminal Growth | H61: 0.02
B62: Terminal EBITDA Multiple 1 | H62: 7
B63: Net Debt ¹⁴ | H63: =Core_Model!L54 + Core_Model!L48 + Core_Model!L55+Core_Model!L62 -> 1388.3175
B65: Taxes & Depreciation
B66: First Year Tax Depreciation | D66: 0.5
B67: Blended Tax Depreciation Rate | D67: 0.15
B68: Tax Basis for Assets | D68: 0
B69: Tax Losses | D69: 0
B70: First Year Accounting Depreciation | D70: 0.5
B71: Useful Life: Existing Assets ² | C71: (Years) | D71: 6.37
B72: Useful Life: New Assets ³ | C72: (Years) | D72: 14.28

Sheet Core_Model
B2: Consolidated Statement of Profit and Loss
B3: =Assumptions!B2 -> Particulars | C3: =Assumptions!C2 | D3: =Assumptions!D2 | E3: =Assumptions!E2 -> 2023 | F3: =Assumptions!F2 -> 2024 | G3: =Assumptions!G2 -> 2025 | H3: =Assumptions!H2 -> 2026 | I3: =Assumptions!I2 -> 2027 | ... L3: =Assumptions!L2 -> 2030
B5: Revenue | E5: 60580 | F5: 61896 | G5: 63121 | H5: =G5*(1+Assumptions!H8) -> 66277.05 | I5: =H5*(1+Assumptions!I8) -> 71711.768 | J5: =I5*(1+Assumptions!J8) -> 77448.71 | K5: =J5*(1+Assumptions!K8) -> 82870.119 | L5: =K5*(1+Assumptions!L8) -> 87842.326
B6: COGS | E6: =(20212+11579-75)*-1 -> -31716 | F6: =(19257+10514-11)*-1 -> -29760 | G6: =(19458+11273-153)*-1 -> -30578 | H6: =G6*(1+Assumptions!H13) -> -32045.744 | I6: =H6*(1+Assumptions!I13) -> -34769.632 | J6: =I6*(1+Assumptions!J13) -> -37412.124 | K6: =J6*(1+Assumptions!K13) -> -39843.912 | L6: =K6*(1+Assumptions!L13) -> -42035.328
B7: Gross Profit | E7: =SUM(E5:E6) -> 28864 | F7: =SUM(F5:F6) -> 32136 | G7: =SUM(G5:G6) -> 32543 | H7: =SUM(H5:H6) -> 34231.306 | I7: =SUM(I5:I6) -> 36942.136 | J7: =SUM(J5:J6) -> 40036.585 | K7: =SUM(K5:K6) -> 43026.207 | L7: =SUM(L5:L6) -> 45806.999
B9: SG&A | E9: -2854 | F9: -3009 | G9: -3077 | H9: =G9*(1+Assumptions!H50) -> -3218.542 | I9: =H9*(1+Assumptions!I50) -> -3366.5949 | J9: =I9*(1+Assumptions!J50) -> -3521.4583 | K9: =J9*(1+Assumptions!K50) -> -3683.4454 | L9: =K9*(1+Assumptions!L50) -> -3852.8839
B10: Other Operating Expenses | E10: -11862 | F10: -14464 | G10: -14615 | H10: =G10*(1+Assumptions!H18) -> -15199.6 | I10: =H10*(1+Assumptions!I18) -> -16339.57 | J10: =I10*(1+Assumptions!J18) -> -17516.019 | K10: =J10*(1+Assumptions!K18) -> -18602.012 | L10: =K10*(1+Assumptions!L18) -> -19625.123
B11: EBITDA | E11: =SUM(E7:E10) -> 14148 | F11: =SUM(F7:F10) -> 14663 | G11: =SUM(G7:G10) -> 14851 | H11: =SUM(H7:H10) -> 15813.164 | I11: =SUM(I7:I10) -> 17235.971 | J11: =SUM(J7:J10) -> 18999.108 | K11: =SUM(K7:K10) -> 20740.749 | L11: =SUM(L7:L10) -> 22328.992
B13: Depreciation | E13: -1137 | F13: -1216 | G13: -1355 | H13: =Schedules!H56*-1 -> -1354.0031 | I13: =Schedules!I56*-1 -> -1456.1106 | J13: =Schedules!J56*-1 -> -1566.591 | K13: =Schedules!K56*-1 -> -1685.9097 | L13: =Schedules!L56*-1 -> -1813.5807
B14: EBIT | E14: =SUM(E11:E13) -> 13011 | F14: =SUM(F11:F13) -> 13447 | G14: =SUM(G11:G13) -> 13496 | H14: =SUM(H11:H13) -> 14459.161 | I14: =SUM(I11:I13) -> 15779.86 | J14: =SUM(J11:J13) -> 17432.517 | K14: =SUM(K11:K13) -> 19054.84 | L14: =SUM(L11:L13) -> 20515.411
B16: Other Income ⁵ | E16: =512-1 -> 511 | F16: =811-4 -> 807 | G16: =1017-8 -> 1009 | H16: =H5*0.015 -> 994.15575 | I16: =I5*0.015 -> 1075.6765 | J16: =J5*0.015 -> 1161.7306 | K16: =K5*0.015 -> 1243.0518 | L16: =L5*0.015 -> 1317.6349
B17: Interest ⁶ | E17: -114 | F17: -334 | G17: -395 | H17: =Schedules!H177 -> 0.05 | I17: =Schedules!I177 -> 0 | J17: =Schedules!J177 -> 0 | K17: =Schedules!K177 -> 0 | L17: =Schedules!L177 -> 2
B18: Exceptional Items | E18: -64 | F18: 6 | G18: 305 | H18: =Schedules!H177 -> 0.05 | I18: =Schedules!I177 -> 0 | J18: =Schedules!J177 -> 0 | K18: =Schedules!K177 -> 0 | L18: =Schedules!L177 -> 2
B19: EBT | E19: =SUM(E14:E18) -> 13344 | F19: =SUM(F14:F18) -> 13926 | G19: =SUM(G14:G18) -> 14415 | H19: =SUM(H14:H18) -> 15453.417 | I19: =SUM(I14:I18) -> 16855.537 | J19: =SUM(J14:J18) -> 18594.248 | K19: =SUM(K14:K18) -> 20297.891 | L19: =SUM(L14:L18) -> 21837.046
B21: Current Tax | E21: -3001 | F21: -3521 | G21: -3620 | H21: =Schedules!H122*-1 -> -4341.4963 | I21: =Schedules!I122*-1 -> -4677.6632 | J21: =Schedules!J122*-1 -> -5106.9678 | K21: =Schedules!K122*-1 -> -5532.3888 | L21: =Schedules!L122*-1 -> -5920.0378
B22: Deferred Tax | E22: -200 | F22: -123 | G22: -124 | H22: =Schedules!H123 -> -323.60796 | I22: =Schedules!I123 -> -295.22364 | J22: =Schedules!J123 -> -272.46344 | K22: =Schedules!K123 -> -254.93707 | L22: =Schedules!L123 -> -242.40582
B23: Total Tax | E23: =SUM(E21:E22) -> -3201 | F23: =SUM(F21:F22) -> -3644 | G23: =SUM(G21:G22) -> -3744 | H23: =SUM(H21:H22) -> -4665.1042 | I23: =SUM(I21:I22) -> -4972.8868 | J23: =SUM(J21:J22) -> -5379.4313 | K23: =SUM(K21:K22) -> -5787.3259 | L23: =SUM(L21:L22) -> -6162.4437
B25: Net Income | E25: =E19+E23 -> 10143 | F25: =F19+F23 -> 10282 | G25: =G19+G23 -> 10671 | H25: =H19+H23 -> 10788.312 | I25: =I19+I23 -> 11882.65 | J25: =J19+J23 -> 13214.816 | K25: =K19+K23 -> 14510.565 | L25: =L19+L23 -> 15674.603
B28: Consolidated Balance Sheet
B29: =B3 -> Particulars | C29: =C3 | D29: =D3 | E29: =E3 -> 2023 | F29: =F3 -> 2024 | G29: =G3 -> 2025 | H29: =H3 -> 2026 | I29: =I3 -> 2027 | ... L29: =L3 -> 2030
B31: ASSETS
B32: Cash | E32: =714 -> 714 | F32: 825 | G32: 6071 | H32: =H102 -> 4685.1783 | I32: =I102 -> 6252.4707 | J32: =J102 -> 8009.3964 | K32: =K102 -> 9692.8083 | L32: =L102 -> 11420.804
B33: Short-Term Bank Deposits | E33: 3964 | F33: 6734 | G33: 1483 | H33: 1483 | I33: 1483 | J33: 1483 | K33: 1483 | L33: 1483
B34: Accounts Receivable | E34: 3079 | F34: 2997 | G34: 3819 | H34: =Schedules!H10 -> 3813.2001 | I34: =Schedules!I10 -> 4125.8825 | J34: =Schedules!J10 -> 4443.7784 | K34: =Schedules!K10 -> 4767.8699 | L34: =Schedules!L10 -> 5053.9421
B35: Inventories | E35: 4251 | F35: 4022 | G35: 4415 | H35: =Schedules!H11 -> 4521.5228 | I35: =Schedules!I11 -> 4905.8522 | J35: =Schedules!J11 -> 5213.1649 | K35: =Schedules!K11 -> 5567.2316 | L35: =Schedules!L11 -> 5873.4293
B36: Other Current Assets ⁷ | D36: =3519+35+1089+688+13 -> 5344 | E36: =2811+36+1386+745+12 -> 4990 | F36: =4558+38+1425+713+12 -> 6746 | G36: =3751+46+1488+955+23 -> 6263 | H36: =H5*0.095 -> 6296.3198 | I36: =I5*0.095 -> 6812.618 | J36: =J5*0.095 -> 7357.6274 | K36: =K5*0.095 -> 7872.6613 | L36: =L5*0.095 -> 8345.021
B37: Total Current Assets | E37: =SUM(E32:E36) -> 16998 | F37: =SUM(F32:F36) -> 21324 | G37: =SUM(G32:G36) -> 22051 | H37: =SUM(H32:H36) -> 20799.221 | I37: =SUM(I32:I36) -> 23579.823 | J37: =SUM(J32:J36) -> 26506.967 | K37: =SUM(K32:K36) -> 29383.571 | L37: =SUM(L32:L36) -> 32176.196
B39: Goodwill | E39: 17466 | F39: 17466 | G39: 17466 | H39: 17466 | I39: 17466 | J39: 17466 | K39: 17466 | L39: 17466
B40: Intangibles ⁸ | E40: 28263 | F40: 28247 | G40: 28244 | H40: =G40*0.97 -> 27396.68 | I40: =H40*0.97 -> 26574.78 | J40: =I40*0.97 -> 25777.536 | K40: =J40*0.97 -> 25004.21 | L40: =K40*0.97 -> 24254.084
B41: Other Non Current Assets | D41: =2+115+729+11+1158+194 -> 2209 | E41: =69+2+98+725+10+1164+211 -> 2279 | F41: =65+2+102+760+10+1175+292 -> 2406 | G41: =57+2+87+763+17+1199+360 -> 2485 | H41: =57+2+87+763+17+1199+360 -> 2485 | I41: =57+2+87+763+17+1199+360 -> 2485 | J41: =57+2+87+763+17+1199+360 -> 2485 | K41: =57+2+87+763+17+1199+360 -> 2485 | L41: =57+2+87+763+17+1199+360 -> 2485
B42: Property Plant & Equipment | E42: =6949+1132 -> 8081 | F42: =8031+1025 -> 9056 | G42: =8625+1009 -> 9634 | H42: =Schedules!H74 -> 9738.092 | I42: =Schedules!I74 -> 9859.6402 | J42: =Schedules!J74 -> 9996.9209 | K42: =Schedules!K74 -> 10134.154 | L42: =Schedules!L74 -> 10253.104
B43: Total Assets | E43: =SUM(E37:E42) -> 73087 | F43: =SUM(F37:F42) -> 78499 | G43: =SUM(G37:G42) -> 79880 | H43: =SUM(H37:H42) -> 77884.993 | I43: =SUM(I37:I42) -> 79965.243 | J43: =SUM(J37:J42) -> 82232.424 | K43: =SUM(K37:K42) -> 84472.935 | L43: =SUM(L37:L42) -> 86634.384
B46: LIABILITIES
B47: Accounts Payable | E47: =100+9474 -> 9574 | F47: =250+10236 -> 10486 | G47: =263+11052 -> 11315 | H47: =Schedules!H12 -> 11676.942 | I47: =Schedules!I12 -> 12669.482 | J47: =Schedules!J12 -> 13697.335 | K47: =Schedules!K12 -> 14627.628 | L47: =Schedules!L12 -> 15432.148
B48: Revolving Credit Line | D48: 0 | E48: 98 | F48: 13 | G48: 1 | H48: =Schedules!H91 -> 0 | I48: =Schedules!I91 -> 0 | J48: =Schedules!J91 -> 0 | K48: =Schedules!K91 -> 0 | L48: =Schedules!L91 -> 0
B49: Other Current Libilities ¹⁰ | D49: =302+889+665+346 -> 2202 | E49: =314+889+764+389 -> 2356 | F49: =365+865+807+340 -> 2377 | G49: =404+1280+959+675+1903 -> 5221 | H49: =H5*0.038 -> 2518.5279 | I49: =I5*0.038 -> 2725.0472 | J49: =J5*0.038 -> 2943.051 | K49: =K5*0.038 -> 3149.0645 | L49: =L5*0.038 -> 3338.0084
B50: Balance Sheet Adjustment | H50: =H43-SUM(H47:H49,H53:H56,H60:H62) -> -170.05672 | I50: =I43-SUM(I47:I49,I53:I56,I60:I62) -> 73.289902 | J50: =J43-SUM(J47:J49,J53:J56,J60:J62) -> 322.17322 | K50: =K43-SUM(K47:K49,K53:K56,K60:K62) -> 527.5425 | L50: =L43-SUM(L47:L49,L53:L56,L60:L62) -> 685.87285
B51: Total Current Liabilities | E51: =SUM(E47:E50) -> 12028 | F51: =SUM(F47:F50) -> 12876 | G51: =SUM(G47:G50) -> 16537 | H51: =SUM(H47:H50) -> 14025.414 | I51: =SUM(I47:I50) -> 15467.82 | J51: =SUM(J47:J50) -> 16962.559 | K51: =SUM(K47:K50) -> 18304.235 | L51: =SUM(L47:L50) -> 19456.029
B53: Deferred Taxes | E53: 6421 | F53: 6557 | G53: 6685 | H53: =G53+H22 -> 6361.392 | I53: =H53+I22 -> 6066.1684 | J53: =I53+J22 -> 5793.705 | K53: =J53+K22 -> 5538.7679 | L53: =K53+L22 -> 5296.3621
B54: Long-Term Debt | E54: 0 | F54: 0 | G54: 0 | H54: =Schedules!H172 -> 0 | I54: =Schedules!I172 -> 0 | J54: =Schedules!J172 -> 0 | K54: =Schedules!K172 -> 0 | L54: =Schedules!L172 -> 0
B55: Lease Libilities | E55: 807 | F55: 1106 | G55: 1243 | H55: =Schedules!H209 -> 1180.85 | I55: =Schedules!I209 -> 1121.8075 | J55: =Schedules!J209 -> 1065.7171 | K55: =Schedules!K209 -> 1012.4313 | L55: =Schedules!L209 -> 961.80971
B56: Other Non Current Libilities | D56: =741+357+1580+1331 -> 4009 | E56: =860+1363+1086 -> 3309 | F56: =718+1576+4243 -> 6537 | G56: =680+1528+3598 -> 5806 | H56: =G56 -> 5806 | I56: =H56 -> 5806 | J56: =I56 -> 5806 | K56: =J56 -> 5806 | L56: =K56 -> 5806
B57: Total Liabilities | E57: =SUM(E51:E56) -> 22565 | F57: =SUM(F51:F56) -> 27076 | G57: =SUM(G51:G56) -> 30271 | H57: =SUM(H51:H56) -> 27373.656 | I57: =SUM(I51:I56) -> 28461.795 | J57: =SUM(J51:J56) -> 29627.981 | K57: =SUM(K51:K56) -> 30661.434 | L57: =SUM(L51:L56) -> 31520.201
B59: EQUITY
B60: Common Equity | D60: 235 | E60: 235 | F60: 235 | G60: 235 | H60: =Schedules!H182 -> 235 | I60: =Schedules!I182 -> 235 | J60: =Schedules!J182 -> 235 | K60: =Schedules!K182 -> 235 | L60: =Schedules!L182 -> 235
B61: Retained Earnings | E61: 50069 | F61: 50983 | G61: 49167 | H61: =Schedules!H188 -> 50030.065 | I61: =Schedules!I188 -> 50980.677 | J61: =Schedules!J188 -> 52037.862 | K61: =Schedules!K188 -> 53198.708 | L61: =Schedules!L188 -> 54452.676
B62: Non Controlling Interest | E62: 218 | F62: 205 | G62: 207 | H62: =Schedules!H194 -> 246.27239 | I62: =Schedules!I194 -> 287.77087 | J62: =Schedules!J194 -> 331.58048 | K62: =Schedules!K194 -> 377.79317 | L62: =Schedules!L194 -> 426.50784
B63: Total Shareholders' Equity | E63: =SUM(E60:E62) -> 50522 | F63: =SUM(F60:F62) -> 51423 | G63: =SUM(G60:G62) -> 49609 | H63: =SUM(H60:H62) -> 50511.337 | I63: =SUM(I60:I62) -> 51503.448 | J63: =SUM(J60:J62) -> 52604.443 | K63: =SUM(K60:K62) -> 53811.501 | L63: =SUM(L60:L62) -> 55114.184
B65: Total Liabilities & Equity | E65: =E57+E63 -> 73087 | F65: =F57+F63 -> 78499 | G65: =G57+G63 -> 79880 | H65: =H57+H63 -> 77884.993 | I65: =I57+I63 -> 79965.243 | J65: =J57+J63 -> 82232.424 | K65: =K57+K63 -> 84472.935 | L65: =L57+L63 -> 86634.384
B67: Consolidated Statement of Cash Flows
B68: =B29 -> Particulars | C68: =C29 | D68: =D29 | E68: =E29 -> 2023 | F68: =F29 -> 2024 | G68: =G29 -> 2025 | H68: =H29 -> 2026 | I68: =I29 -> 2027 | ... L68: =L29 -> 2030
B70: CASH FROM OPERATIONS
B71: Net Income | E71: =E25 -> 10143 | F71: =F25 -> 10282 | G71: =G25 -> 10671 | H71: =H25 -> 10788.312 | I71: =I25 -> 11882.65 | J71: =J25 -> 13214.816 | K71: =K25 -> 14510.565 | L71: =L25 -> 15674.603
B72: Deferred Taxes | E72: =E22*-1 -> 200 | F72: =F22*-1 -> 123 | G72: =G22*-1 -> 124 | H72: =H22*-1 -> 323.60796 | I72: =I22*-1 -> 295.22364 | J72: =J22*-1 -> 272.46344 | K72: =K22*-1 -> 254.93707 | L72: =L22*-1 -> 242.40582
B73: Depreciation | E73: 1152 | F73: 1216 | G73: 1363 | H73: =H13*-1 -> 1354.0031 | I73: =I13*-1 -> 1456.1106 | J73: =J13*-1 -> 1566.591 | K73: =K13*-1 -> 1685.9097 | L73: =L13*-1 -> 1813.5807
B74: Cash From Other Current Liabilities | E74: 0 | F74: 0 | G74: 0 | H74: =H49-G49 -> -2702.4721 | I74: =I49-H49 -> 206.51929 | J74: =J49-I49 -> 218.00378 | K74: =K49-J49 -> 206.01357 | L74: =L49-K49 -> 188.94387
B75: Non-Cash & Non-Operating Adjustments | E75: =-100-2-411-2-99+114+1-60-1+2+184-27-8 -> -409 | F75: =18-132-546-3-249+317-159-1+4+167-11-10 -> -605 | G75: =43+120-755-256+372-559-1+8+189+24+11+4 -> -800 | H75: 0 | I75: 0 | J75: 0 | K75: 0 | L75: 0
B76: Current Assets/Liabilities Residual | E76: =(622-ABS(E80))+(-(1111-ABS(E78)-ABS(E79))) -> 3 | F76: =(921-ABS(F80))+((220-ABS(F78)-ABS(F79))) -> -82 | G76: =(1442-ABS(G80))+(-(1275-ABS(G78)-ABS(G79))) -> 553 | H76: 0 | I76: 0 | J76: 0 | K76: 0 | L76: 0
B77: Cash From Other Current/Non-Current Items | E77: =-14-339-116+(3001-3138) -> -606 | F77: =-30+74+128+(3521-381) -> 3312 | G77: =-87-584-284+(3620-2268) -> 397 | H77: 0 | I77: 0 | J77: 0 | K77: 0 | L77: 0
B78: Cash From Accounts Receivable | E78: =Schedules!E15 -> -843 | F78: =Schedules!F15 -> 82 | G78: =Schedules!G15 -> -822 | H78: =Schedules!H15 -> 5.799863 | I78: =Schedules!I15 -> -312.68241 | J78: =Schedules!J15 -> -317.89587 | K78: =Schedules!K15 -> -324.09146 | L78: =Schedules!L15 -> -286.07219
B79: Cash From Inventory | E79: =Schedules!E16 -> -155 | F79: =Schedules!F16 -> 229 | G79: =Schedules!G16 -> -393 | H79: =Schedules!H16 -> -106.52278 | I79: =Schedules!I16 -> -384.32944 | J79: =Schedules!J16 -> -307.31264 | K79: =Schedules!K16 -> -354.06673 | L79: =Schedules!L16 -> -306.19774
B80: Cash From Accounts Payable | E80: =Schedules!E17 -> 506 | F80: =Schedules!F17 -> 912 | G80: =Schedules!G17 -> 829 | H80: =Schedules!H17 -> 361.94233 | I80: =Schedules!I17 -> 992.5401 | J80: =Schedules!J17 -> 1027.8527 | K80: =Schedules!K17 -> 930.29298 | L80: =Schedules!L17 -> 804.51955
B81: Subtotal | E81: =SUM(E71:E80) -> 9991 | F81: =SUM(F71:F80) -> 15469 | G81: =SUM(G71:G80) -> 11922 | H81: =SUM(H71:H80) -> 10024.671 | I81: =SUM(I71:I80) -> 14136.032 | J81: =SUM(J71:J80) -> 15674.519 | K81: =SUM(K71:K80) -> 16909.561 | L81: =SUM(L71:L80) -> 18131.783
B83: CASH FROM INVESTING
B84: Capital Expenditure | E84: =-1174-18+121+60 -> -1011 | F84: =-1468-9+20 -> -1457 | G84: =-1254-21+13+595 -> -667 | H84: =Assumptions!H38*-1 -> -1458.0951 | I84: =Assumptions!I38*-1 -> -1577.6589 | J84: =Assumptions!J38*-1 -> -1703.8716 | K84: =Assumptions!K38*-1 -> -1823.1426 | L84: =Assumptions!L38*-1 -> -1932.5312
B85: Net Investments | E85: =-264-2-70-40-22649+23462 -> 437 | F85: =-4-21337+19846 -> -1495 | G85: =-22957+23987 -> 1030 | H85: 0 | I85: 0 | J85: 0 | K85: 0 | L85: 0
B86: Net Loans & Deposits | E86: =-1-3668+2488+259+2 -> -920 | F86: =1-9170+6369+425+3 -> -2372 | G86: =-2499+7774+835 -> 6110 | H86: 0 | I86: 0 | J86: 0 | K86: 0 | L86: 0
B87: Subtotal | E87: =SUM(E84:E86) -> -1494 | F87: =SUM(F84:F86) -> -5324 | G87: =SUM(G84:G86) -> 6473 | H87: =SUM(H84:H86) -> -1458.0951 | I87: =SUM(I84:I86) -> -1577.6589 | J87: =SUM(J84:J86) -> -1703.8716 | K87: =SUM(K84:K86) -> -1823.1426 | L87: =SUM(L84:L86) -> -1932.5312
B89: CASH FROM FINANCING
B90: Short-Term Borrowings | E90: =286-201-7 -> 78 | F90: =-85 -> -85 | G90: 0 | H90: 0 | I90: 0 | J90: 0 | K90: 0 | L90: 0
B91: Lease Financing ¹² | E91: =-467-84 -> -551 | F91: =-423-106 -> -529 | G91: =-498-127 -> -625 | H91: =Schedules!H208 -> -62.15 | I91: =Schedules!I208 -> -59.0425 | J91: =Schedules!J208 -> -56.090375 | K91: =Schedules!K208 -> -53.285856 | L91: =Schedules!L208 -> -50.621563
B92: Other Financing Charges | E92: =-4-2 -> -6 | F92: -4 | G92: -3 | H92: 0 | I92: 0 | J92: 0 | K92: 0 | L92: 0
B93: Dividends | E93: =-8474 -> -8474 | F93: -9416 | G93: -12473 | H93: =Schedules!H187 -> -9925.2474 | I93: =Schedules!I187 -> -10932.038 | J93: =Schedules!J187 -> -12157.631 | K93: =Schedules!K187 -> -13349.72 | L93: =Schedules!L187 -> -14420.634
B94: Change in Long-Term Debt | E94: 0 | F94: 0 | G94: 0 | H94: =Assumptions!H51 -> 0 | I94: =Assumptions!I51 -> 0 | J94: =Assumptions!J51 -> 0 | K94: =Assumptions!K51 -> 0 | L94: =Assumptions!L51 -> 0
B95: Change in Common Equity | E95: 0 | F95: 0 | G95: 0 | H95: =Assumptions!H52 -> 0 | I95: =Assumptions!I52 -> 0 | J95: =Assumptions!J52 -> 0 | K95: =Assumptions!K52 -> 0 | L95: =Assumptions!L52 -> 0
B96: Subtotal | E96: =SUM(E90:E93) -> -8953 | F96: =SUM(F90:F93) -> -10034 | G96: =SUM(G90:G93) -> -13101 | H96: =SUM(H90:H93) -> -9987.3974 | I96: =SUM(I90:I93) -> -10991.08 | J96: =SUM(J90:J93) -> -12213.721 | K96: =SUM(K90:K93) -> -13403.006 | L96: =SUM(L90:L93) -> -14471.256
B98: CASH BALANCE
B99: Beginning of the Year | E99: =1147 -> 1147 | F99: =E102 -> 701 | G99: =F102 -> 812 | H99: =G102 -> 6106 | I99: =H102 -> 4685.1783 | J99: =I102 -> 6252.4707 | K99: =J102 -> 8009.3964 | L99: =K102 -> 9692.8083
B100: Increase / (Decrease) | E100: =E81+E87+E96 -> -456 | F100: =F81+F87+F96 -> 111 | G100: =G81+G87+G96 -> 5294 | H100: =H81+H87+H96 -> -1420.8217 | I100: =I81+I87+I96 -> 1567.2924 | J100: =J81+J87+J96 -> 1756.9257 | K100: =K81+K87+K96 -> 1683.4119 | L100: =L81+L87+L96 -> 1727.9955
B101: cash acquired under business combination | E101: 10 | F101: 0 | G101: 0 | H101: =G101 -> 0 | I101: =H101 -> 0 | J101: =I101 -> 0 | K101: =J101 -> 0 | L101: =K101 -> 0
B102: End of the Year | E102: =SUM(E99:E101) -> 701 | F102: =SUM(F99:F101) -> 812 | G102: =SUM(G99:G101) -> 6106 | H102: =SUM(H99:H101) -> 4685.1783 | I102: =SUM(I99:I101) -> 6252.4707 | J102: =SUM(J99:J101) -> 8009.3964 | K102: =SUM(K99:K101) -> 9692.8083 | L102: =SUM(L99:L101) -> 11420.804
B104: NOTE
B106: Cash Defination for CFS | E106: =E68 -> 2023 | F106: =F68 -> 2024 | G106: =G68 -> 2025 | H106: =H68 -> 2026 | I106: =I68 -> 2027 | J106: =J68 -> 2028 | K106: =K68 -> 2029 | L106: =L68 -> 2030
B107: Cash as per BS | E107: =E32 -> 714 | F107: =F32 -> 825 | G107: =G32 -> 6071 | H107: =H32 -> 4685.1783 | I107: =I32 -> 6252.4707 | J107: =J32 -> 8009.3964 | K107: =K32 -> 9692.8083 | L107: =L32 -> 11420.804
B108: Bank Overdraft (HUL AR Note 23) | E108: -13 | F108: -13 | G108: -1 | H108: 0 | I108: 0 | J108: 0 | K108: 0 | L108: 0
B109: End of the Year | E109: =SUM(E107:E108) -> 701 | F109: =SUM(F107:F108) -> 812 | G109: =SUM(G107:G108) -> 6070 | H109: =SUM(H107:H108) -> 4685.1783 | I109: =SUM(I107:I108) -> 6252.4707 | J109: =SUM(J107:J108) -> 8009.3964 | K109: =SUM(K107:K108) -> 9692.8083 | L109: =SUM(L107:L108) -> 11420.804

Sheet Schedules
B2: Working Capital Schedule
B3: =Assumptions!B2 -> Particulars | C3: =Assumptions!C2 | D3: =Assumptions!D2 | E3: =Assumptions!E2 -> 2023 | F3: =Assumptions!F2 -> 2024 | G3: =Assumptions!G2 -> 2025 | H3: =Assumptions!H2 -> 2026 | I3: =Assumptions!I2 -> 2027 | ... L3: =Assumptions!L2 -> 2030
B5: Days in Period | E5: =Assumptions!E49 -> 365 | F5: =Assumptions!F49 -> 365 | G5: =Assumptions!G49 -> 365 | H5: =Assumptions!H49 -> 365 | I5: =Assumptions!I49 -> 365 | J5: =Assumptions!J49 -> 366 | K5: =Assumptions!K49 -> 365 | L5: =Assumptions!L49 -> 365
B6: Revenue | E6: =Core_Model!E5 -> 60580 | F6: =Core_Model!F5 -> 61896 | G6: =Core_Model!G5 -> 63121 | H6: =Core_Model!H5 -> 66277.05 | I6: =Core_Model!I5 -> 71711.768 | J6: =Core_Model!J5 -> 77448.71 | K6: =Core_Model!K5 -> 82870.119 | L6: =Core_Model!L5 -> 87842.326
B7: COGS | E7: =Core_Model!E6*-1 -> 31716 | F7: =Core_Model!F6*-1 -> 29760 | G7: =Core_Model!G6*-1 -> 30578 | H7: =Core_Model!H6*-1 -> 32045.744 | I7: =Core_Model!I6*-1 -> 34769.632 | J7: =Core_Model!J6*-1 -> 37412.124 | K7: =Core_Model!K6*-1 -> 39843.912 | L7: =Core_Model!L6*-1 -> 42035.328
B9: TOTAL AMOUNTS
B10: Accounts Receivable | D10: 2236 | E10: =Core_Model!E34 -> 3079 | F10: =Core_Model!F34 -> 2997 | G10: =Core_Model!G34 -> 3819 | H10: =(H6*H21)/H5 -> 3813.2001 | I10: =(I6*I21)/I5 -> 4125.8825 | J10: =(J6*J21)/J5 -> 4443.7784 | K10: =(K6*K21)/K5 -> 4767.8699 | L10: =(L6*L21)/L5 -> 5053.9421
B11: Inventories | D11: 4096 | E11: =Core_Model!E35 -> 4251 | F11: =Core_Model!F35 -> 4022 | G11: =Core_Model!G35 -> 4415 | H11: =(H7*H22)/H5 -> 4521.5228 | I11: =(I7*I22)/I5 -> 4905.8522 | J11: =(J7*J22)/J5 -> 5213.1649 | K11: =(K7*K22)/K5 -> 5567.2316 | L11: =(L7*L22)/L5 -> 5873.4293
B12: Accounts Payable | D12: 9068 | E12: =Core_Model!E47 -> 9574 | F12: =Core_Model!F47 -> 10486 | G12: =Core_Model!G47 -> 11315 | H12: =(H7*H23)/H5 -> 11676.942 | I12: =(I7*I23)/I5 -> 12669.482 | J12: =(J7*J23)/J5 -> 13697.335 | K12: =(K7*K23)/K5 -> 14627.628 | L12: =(L7*L23)/L5 -> 15432.148
B14: CASH CHANGES
B15: Accounts Receivable | E15: =(E10-D10)*-1 -> -843 | F15: =(F10-E10)*-1 -> 82 | G15: =(G10-F10)*-1 -> -822 | H15: =(H10-G10)*-1 -> 5.799863 | I15: =(I10-H10)*-1 -> -312.68241 | J15: =(J10-I10)*-1 -> -317.89587 | K15: =(K10-J10)*-1 -> -324.09146 | L15: =(L10-K10)*-1 -> -286.07219
B16: Inventories | E16: =(E11-D11)*-1 -> -155 | F16: =(F11-E11)*-1 -> 229 | G16: =(G11-F11)*-1 -> -393 | H16: =(H11-G11)*-1 -> -106.52278 | I16: =(I11-H11)*-1 -> -384.32944 | J16: =(J11-I11)*-1 -> -307.31264 | K16: =(K11-J11)*-1 -> -354.06673 | L16: =(L11-K11)*-1 -> -306.19774
B17: Accounts Payable | E17: =E12-D12 -> 506 | F17: =F12-E12 -> 912 | G17: =G12-F12 -> 829 | H17: =H12-G12 -> 361.94233 | I17: =I12-H12 -> 992.5401 | J17: =J12-I12 -> 1027.8527 | K17: =K12-J12 -> 930.29298 | L17: =L12-K12 -> 804.51955
B18: Cash from Working Capital Items | E18: =SUM(E15:E17) -> -492 | F18: =SUM(F15:F17) -> 1223 | G18: =SUM(G15:G17) -> -386 | H18: =SUM(H15:H17) -> 261.21941 | I18: =SUM(I15:I17) -> 295.52825 | J18: =SUM(J15:J17) -> 402.64418 | K18: =SUM(K15:K17) -> 252.13479 | L18: =SUM(L15:L17) -> 212.24962
B20: PER DAY
B21: Accounts Receivable | H21: =Assumptions!H23 -> 21 | I21: =Assumptions!I23 -> 21 | J21: =Assumptions!J23 -> 21 | K21: =Assumptions!K23 -> 21 | L21: =Assumptions!L23 -> 21
B22: Inventories | H22: =Assumptions!H28 -> 51.5 | I22: =Assumptions!I28 -> 51.5 | J22: =Assumptions!J28 -> 51 | K22: =Assumptions!K28 -> 51 | L22: =Assumptions!L28 -> 51
B23: Accounts Payable | H23: =Assumptions!H33 -> 133 | I23: =Assumptions!I33 -> 133 | J23: =Assumptions!J33 -> 134 | K23: =Assumptions!K33 -> 134 | L23: =Assumptions!L33 -> 134
B25: Depreciation Schedule
B26: =B3 -> Particulars | C26: =C3 | D26: =D3 | H26: =H3 -> 2026 | I26: =I3 -> 2027 | J26: =J3 -> 2028 | K26: =K3 -> 2029 | L26: =L3 -> 2030
B28: Capital Expenditure | H28: =Assumptions!H38 -> 1458.0951 | I28: =Assumptions!I38 -> 1577.6589 | J28: =Assumptions!J38 -> 1703.8716 | K28: =Assumptions!K38 -> 1823.1426 | L28: =Assumptions!L38 -> 1932.5312
B31: EXISTING ASSETS 1 | H31: Percent of Full Year
B32: Useful Life | C32: (Years) | D32: =Assumptions!D71 -> 6.37 | H32: 1 | I32: =H32+1 -> 2 | J32: =I32+1 -> 3 | K32: =J32+1 -> 4 | L32: =K32+1 -> 5
B33: PP&E | C33: =CONCATENATE("(End of ",G26,")") -> (End of ) | D33: =Core_Model!G42-1009 -> 8625 | H33: =MIN($D32-SUM($G33:G33),1) -> 1 | I33: =MIN($D32-SUM($G33:H33),1) -> 1 | J33: =MIN($D32-SUM($G33:I33),1) -> 1 | K33: =MIN($D32-SUM($G33:J33),1) -> 1 | L33: =MIN($D32-SUM($G33:K33),1) -> 1
H36: Percent of Full Year
B37: NEW ASSETS 1 | H37: =H26 -> 2026 | I37: =I26 -> 2027 | J37: =J26 -> 2028 | K37: =K26 -> 2029 | L37: =L26 -> 2030
B38: Useful Life | C38: (Years) | D38: =Assumptions!D72 -> 14.28 | H38: =IF(G38="",$D$224,MIN($D38-SUM($G38:G38),1)) -> 0 | I38: =IF(H38="",$D$224,MIN($D38-SUM($G38:H38),1)) -> 1 | J38: =IF(I38="",$D$224,MIN($D38-SUM($G38:I38),1)) -> 1 | K38: =IF(J38="",$D$224,MIN($D38-SUM($G38:J38),1)) -> 1 | L38: =IF(K38="",$D$224,MIN($D38-SUM($G38:K38),1)) -> 1
B39: First Year Amount | D39: =Assumptions!D70 -> 0.5 | H39: =G38 -> 0 | I39: =H38 -> 0 | J39: =I38 -> 1 | K39: =J38 -> 1 | L39: =K38 -> 1
H40: =G39 -> 0 | I40: =H39 -> 0 | J40: =I39 -> 0 | K40: =J39 -> 1 | L40: =K39 -> 1
H41: =G40 -> 0 | I41: =H40 -> 0 | J41: =I40 -> 0 | K41: =J40 -> 0 | L41: =K40 -> 1
H42: =G41 -> 0 | I42: =H41 -> 0 | J42: =I41 -> 0 | K42: =J41 -> 0 | L42: =K41 -> 0
H45: Amounts for Depreciation
E46: Year | F46: Capex | G46: Per Yr | H46: =H37 -> 2026 | I46: =I37 -> 2027 | J46: =J37 -> 2028 | K46: =K37 -> 2029 | L46: =L37 -> 2030
E47: {=TRANSPOSE(H26:L26)} -> 2026 | F47: =SUMIF($H$26:$L$26,E47,$H$28:$L$28) -> 1458.0951 | G47: =F47/$D$38 -> 102.1075 | H47: =$G47*H38 -> 0 | I47: =$G47*I38 -> 102.1075 | J47: =$G47*J38 -> 102.1075 | K47: =$G47*K38 -> 102.1075 | L47: =$G47*L38 -> 102.1075
E48: 2027 | F48: =SUMIF($H$26:$L$26,E48,$H$28:$L$28) -> 1577.6589 | G48: =F48/$D$38 -> 110.48031 | H48: =$G48*H39 -> 0 | I48: =$G48*I39 -> 0 | J48: =$G48*J39 -> 110.48031 | K48: =$G48*K39 -> 110.48031 | L48: =$G48*L39 -> 110.48031
E49: 2028 | F49: =SUMIF($H$26:$L$26,E49,$H$28:$L$28) -> 1703.8716 | G49: =F49/$D$38 -> 119.31874 | H49: =$G49*H40 -> 0 | I49: =$G49*I40 -> 0 | J49: =$G49*J40 -> 0 | K49: =$G49*K40 -> 119.31874 | L49: =$G49*L40 -> 119.31874
E50: 2029 | F50: =SUMIF($H$26:$L$26,E50,$H$28:$L$28) -> 1823.1426 | G50: =F50/$D$38 -> 127.67105 | H50: =$G50*H41 -> 0 | I50: =$G50*I41 -> 0 | J50: =$G50*J41 -> 0 | K50: =$G50*K41 -> 0 | L50: =$G50*L41 -> 127.67105
E51: 2030 | F51: =SUMIF($H$26:$L$26,E51,$H$28:$L$28) -> 1932.5312 | G51: =F51/$D$38 -> 135.33132 | H51: =$G51*H42 -> 0 | I51: =$G51*I42 -> 0 | J51: =$G51*J42 -> 0 | K51: =$G51*K42 -> 0 | L51: =$G51*L42 -> 0
B53: TOTAL ASSET DEPRECIATION 2
B54: Existing Assets | H54: =($D$33/$D$32)*H33 -> 1354.0031 | I54: =($D$33/$D$32)*I33 -> 1354.0031 | J54: =($D$33/$D$32)*J33 -> 1354.0031 | K54: =($D$33/$D$32)*K33 -> 1354.0031 | L54: =($D$33/$D$32)*L33 -> 1354.0031
B55: New Assets | H55: =SUM(H47:H51) -> 0 | I55: =SUM(I47:I51) -> 102.1075 | J55: =SUM(J47:J51) -> 212.58781 | K55: =SUM(K47:K51) -> 331.90656 | L55: =SUM(L47:L51) -> 459.57761
B56: Total Depreciation | H56: =SUM(H54:H55) -> 1354.0031 | I56: =SUM(I54:I55) -> 1456.1106 | J56: =SUM(J54:J55) -> 1566.591 | K56: =SUM(K54:K55) -> 1685.9097 | L56: =SUM(L54:L55) -> 1813.5807
B58: PP&E Schedule
B59: =B3 -> Particulars | C59: =C3 | D59: =D3 | E59: =E3 -> 2023 | F59: =F3 -> 2024 | G59: =G3 -> 2025 | H59: =H3 -> 2026 | I59: =I3 -> 2027 | ... L59: =L3 -> 2030
B61: PROPERTY PLANT & EQUIPMENT
B62: Beginning | H62: =G66 -> 8625 | I62: =H66 -> 8510.3777 | J62: =I66 -> 8613.9914 | K62: =J66 -> 8732.3401 | L62: =K66 -> 8851.6824
B63: Capitalized PP&E ⁹ | H63: =Assumptions!H38*0.85 -> 1239.3808 | I63: =Assumptions!I38*0.85 -> 1341.0101 | J63: =Assumptions!J38*0.85 -> 1448.2909 | K63: =Assumptions!K38*0.85 -> 1549.6712 | L63: =Assumptions!L38*0.85 -> 1642.6515
B64: Transfers to PP&E | H64: =H71*-1 -> 0 | I64: =I71*-1 -> 218.71426 | J64: =J71*-1 -> 236.64883 | K64: =K71*-1 -> 255.58074 | L64: =L71*-1 -> 273.47139
B65: Depreciation | H65: =H56*-1 -> -1354.0031 | I65: =I56*-1 -> -1456.1106 | J65: =J56*-1 -> -1566.591 | K65: =K56*-1 -> -1685.9097 | L65: =L56*-1 -> -1813.5807
B66: Ending | G66: =Core_Model!G42-1009 -> 8625 | H66: =SUM(H62:H65) -> 8510.3777 | I66: =SUM(I62:I65) -> 8613.9914 | J66: =SUM(J62:J65) -> 8732.3401 | K66: =SUM(K62:K65) -> 8851.6824 | L66: =SUM(L62:L65) -> 8954.2246
B68: CWIP PP&E
B69: Beginning | H69: =G72 -> 1009 | I69: =H72 -> 1227.7143 | J69: =I72 -> 1245.6488 | K69: =J72 -> 1264.5807 | L69: =K72 -> 1282.4714
B70: Capitalized CWIP | H70: =Assumptions!H38*0.15 -> 218.71426 | I70: =Assumptions!I38*0.15 -> 236.64883 | J70: =Assumptions!J38*0.15 -> 255.58074 | K70: =Assumptions!K38*0.15 -> 273.47139 | L70: =Assumptions!L38*0.15 -> 289.87968
B71: Transfers to PP&E | H71: =G70*-1 -> 0 | I71: =H70*-1 -> -218.71426 | J71: =I70*-1 -> -236.64883 | K71: =J70*-1 -> -255.58074 | L71: =K70*-1 -> -273.47139
B72: Ending | G72: =Core_Model!G42-Schedules!G66 -> 1009 | H72: =SUM(H69:H71) -> 1227.7143 | I72: =SUM(I69:I71) -> 1245.6488 | J72: =SUM(J69:J71) -> 1264.5807 | K72: =SUM(K69:K71) -> 1282.4714 | L72: =SUM(L69:L71) -> 1298.8797
B74: Total Assets | H74: =H66+H72 -> 9738.092 | I74: =I66+I72 -> 9859.6402 | J74: =J66+J72 -> 9996.9209 | K74: =K66+K72 -> 10134.154 | L74: =L66+L72 -> 10253.104
B76: Revolving Credit Line Schedule
B77: =B59 -> Particulars | C77: =C59 | D77: =D59 | E77: =E59 -> 2023 | F77: =F59 -> 2024 | G77: =G59 -> 2025 | H77: =H59 -> 2026 | I77: =I59 -> 2027 | ... L77: =L59 -> 2030
B79: AVAILABLE CASH
B80: Beginning Cash Balance | H80: =Core_Model!H99 -> 6106 | I80: =Core_Model!I99 -> 4685.1783 | J80: =Core_Model!J99 -> 6252.4707 | K80: =Core_Model!K99 -> 8009.3964 | L80: =Core_Model!L99 -> 9692.8083
B81: Cash from Operations | H81: =Core_Model!H81 -> 10024.671 | I81: =Core_Model!I81 -> 14136.032 | J81: =Core_Model!J81 -> 15674.519 | K81: =Core_Model!K81 -> 16909.561 | L81: =Core_Model!L81 -> 18131.783
B82: Cash from Investing | H82: =Core_Model!H87 -> -1458.0951 | I82: =Core_Model!I87 -> -1577.6589 | J82: =Core_Model!J87 -> -1703.8716 | K82: =Core_Model!K87 -> -1823.1426 | L82: =Core_Model!L87 -> -1932.5312
B83: Change in Long-Term Debt | H83: =Core_Model!H94 -> 0 | I83: =Core_Model!I94 -> 0 | J83: =Core_Model!J94 -> 0 | K83: =Core_Model!K94 -> 0 | L83: =Core_Model!L94 -> 0
B84: Change in Common Equity | H84: =Core_Model!H95 -> 0 | I84: =Core_Model!I95 -> 0 | J84: =Core_Model!J95 -> 0 | K84: =Core_Model!K95 -> 0 | L84: =Core_Model!L95 -> 0
B85: Dividends | H85: =Core_Model!H93 -> -9925.2474 | I85: =Core_Model!I93 -> -10932.038 | J85: =Core_Model!J93 -> -12157.631 | K85: =Core_Model!K93 -> -13349.72 | L85: =Core_Model!L93 -> -14420.634
B86: Cash Available for Revolving Credit Line | H86: =SUM(H80:H85) -> 4747.3283 | I86: =SUM(I80:I85) -> 6311.5132 | J86: =SUM(J80:J85) -> 8065.4868 | K86: =SUM(K80:K85) -> 9746.0941 | L86: =SUM(L80:L85) -> 11471.425
B88: REVOLVING CREDIT LINE
B89: Beginning Balance | H89: =G91 -> 1 | I89: =H91 -> 0 | J89: =I91 -> 0 | K89: =J91 -> 0 | L89: =K91 -> 0
B90: Increase / (Decrease) | H90: =MIN(H89,H86)*-1 -> -1 | I90: =MIN(I89,I86)*-1 -> 0 | J90: =MIN(J89,J86)*-1 -> 0 | K90: =MIN(K89,K86)*-1 -> 0 | L90: =MIN(L89,L86)*-1 -> 0
B91: Ending Balance | G91: =Core_Model!G48 -> 1 | H91: =SUM(H89:H90) -> 0 | I91: =SUM(I89:I90) -> 0 | J91: =SUM(J89:J90) -> 0 | K91: =SUM(K89:K90) -> 0 | L91: =SUM(L89:L90) -> 0
B93: Interest Expense | H93: =Assumptions!H55*H89 -> 0.05 | I93: =Assumptions!I55*I89 -> 0 | J93: =Assumptions!J55*J89 -> 0 | K93: =Assumptions!K55*K89 -> 0 | L93: 2
B95: Income Tax (Levered) Schedule
B96: =B77 -> Particulars | C96: =C77 | D96: =D77 | E96: =E77 -> 2023 | F96: =F77 -> 2024 | G96: =G77 -> 2025 | H96: =H77 -> 2026 | I96: =I77 -> 2027 | ... L96: =L77 -> 2030
B98: Tax Rate | D98: =Assumptions!H53 -> 0.26
B99: Unused Tax Losses Remaining? | D99: =IF(L119=0,0,1) -> 0
B101: Earnings Before Tax (EBT) | H101: =Core_Model!H19 -> 15453.417 | I101: =Core_Model!I19 -> 16855.537 | J101: =Core_Model!J19 -> 18594.248 | K101: =Core_Model!K19 -> 20297.891 | L101: =Core_Model!L19 -> 21837.046
B102: Profitable Before Taxes? | H102: =IF(H108>0,1,0) -> 1 | I102: =IF(I108>0,1,0) -> 1 | J102: =IF(J108>0,1,0) -> 1 | K102: =IF(K108>0,1,0) -> 1 | L102: =IF(L108>0,1,0) -> 1
B104: ADJUSTMENT FOR DEPRECIATION
B105: EBT | H105: =H101 -> 15453.417 | I105: =I101 -> 16855.537 | J105: =J101 -> 18594.248 | K105: =K101 -> 20297.891 | L105: =L101 -> 21837.046
B106: Add: Depreciation | H106: =Core_Model!H13*-1 -> 1354.0031 | I106: =Core_Model!I13*-1 -> 1456.1106 | J106: =Core_Model!J13*-1 -> 1566.591 | K106: =Core_Model!K13*-1 -> 1685.9097 | L106: =Core_Model!L13*-1 -> 1813.5807
B107: Less: Tax Depreciation | H107: =H166 -> -109.35713 | I107: =I166 -> -320.63511 | J107: =J166 -> -518.65463 | K107: =K166 -> -705.38251 | L107: =L166 -> -881.25067
B108: EBT After Adjustment | H108: =SUM(H105:H107) -> 16698.063 | I108: =SUM(I105:I107) -> 17991.012 | J108: =SUM(J105:J107) -> 19642.184 | K108: =SUM(K105:K107) -> 21278.419 | L108: =SUM(L105:L107) -> 22769.376
B110: ADJUSTMENT FOR TAX LOSSES 1
B111: EBT After Adjustment | H111: =H108 -> 16698.063 | I111: =I108 -> 17991.012 | J111: =J108 -> 19642.184 | K111: =K108 -> 21278.419 | L111: =L108 -> 22769.376
B112: Less: Use of Tax Losses 2 | H112: =H118 -> 0 | I112: =I118 -> 0 | J112: =J118 -> 0 | K112: =K118 -> 0 | L112: =L118 -> 0
B113: Taxable Income | H113: =MAX(SUM(H111:H112),0) -> 16698.063 | I113: =MAX(SUM(I111:I112),0) -> 17991.012 | J113: =MAX(SUM(J111:J112),0) -> 19642.184 | K113: =MAX(SUM(K111:K112),0) -> 21278.419 | L113: =MAX(SUM(L111:L112),0) -> 22769.376
B115: TAX LOSSES
B116: Beginning | H116: =G119 -> 0 | I116: =H119 -> 0 | J116: =I119 -> 0 | K116: =J119 -> 0 | L116: =K119 -> 0
B117: Add: New Losses | H117: =-MIN(H105,0) -> 0 | I117: =-MIN(I105,0) -> 0 | J117: =-MIN(J105,0) -> 0 | K117: =-MIN(K105,0) -> 0 | L117: =-MIN(L105,0) -> 0
B118: Less: Use of Tax Losses | H118: =-MIN(H116,H111)*H102 -> 0 | I118: =-MIN(I116,I111)*I102 -> 0 | J118: =-MIN(J116,J111)*J102 -> 0 | K118: =-MIN(K116,K111)*K102 -> 0 | L118: =-MIN(L116,L111)*L102 -> 0
B119: Ending | G119: =Assumptions!D69 -> 0 | H119: =SUM(H116:H118) -> 0 | I119: =SUM(I116:I118) -> 0 | J119: =SUM(J116:J118) -> 0 | K119: =SUM(K116:K118) -> 0 | L119: =SUM(L116:L118) -> 0
B121: TAXES
B122: Current Taxes | H122: =$D$98*H113 -> 4341.4963 | I122: =$D$98*I113 -> 4677.6632 | J122: =$D$98*J113 -> 5106.9678 | K122: =$D$98*K113 -> 5532.3888 | L122: =$D$98*L113 -> 5920.0378
B123: Deferred Taxes | H123: =H124-H122 -> -323.60796 | I123: =I124-I122 -> -295.22364 | J123: =J124-J122 -> -272.46344 | K123: =K124-K122 -> -254.93707 | L123: =L124-L122 -> -242.40582
B124: Total Taxes | H124: =MAX($D$98*H105,0) -> 4017.8883 | I124: =MAX($D$98*I105,0) -> 4382.4396 | J124: =MAX($D$98*J105,0) -> 4834.5044 | K124: =MAX($D$98*K105,0) -> 5277.4517 | L124: =MAX($D$98*L105,0) -> 5677.632
B126: Income Tax (Unlevered) Schedule
B127: =B96 -> Particulars | C127: =C96 | D127: =D96 | E127: =E96 -> 2023 | F127: =F96 -> 2024 | G127: =G96 -> 2025 | H127: =H96 -> 2026 | I127: =I96 -> 2027 | ... L127: =L96 -> 2030
B129: Tax Rate | D129: =Assumptions!H53 -> 0.26
B130: Unused Tax Losses Remaining? | D130: =IF(L150=0,0,1) -> 0
B132: Earnings Before Interest & Tax (EBIT) | H132: =Core_Model!H14 -> 14459.161 | I132: =Core_Model!I14 -> 15779.86 | J132: =Core_Model!J14 -> 17432.517 | K132: =Core_Model!K14 -> 19054.84 | L132: =Core_Model!L14 -> 20515.411
...

Sheet Valuation_DCF
B2: Unlevered Free Cash Flow Schedule
B3: =Assumptions!B2 -> Particulars | C3: =Assumptions!C2 | D3: =Assumptions!D2 | H3: =Assumptions!H2 -> 2026 | I3: =Assumptions!I2 -> 2027 | J3: =Assumptions!J2 -> 2028 | K3: =Assumptions!K2 -> 2029 | L3: =Assumptions!L2 -> 2030
B5: TAX SHIELD FROM INTEREST | E5: Line Item | F5: Term
B6: Current Taxes (Unlevered) | E6: EBIT | F6: =Core_Model!H14 -> 14459.161 | H6: =Schedules!H153 -> 4082.9898 | I6: =Schedules!I153 -> 4397.9873 | J6: =Schedules!J153 -> 4804.9179 | K6: =Schedules!K153 -> 5209.1954 | L6: =Schedules!L153 -> 5576.4128
B7: Current Taxes (Levered) | E7: EBT | F7: =Core_Model!H19 -> 15453.417 | H7: =Schedules!H122 -> 4341.4963 | I7: =Schedules!I122 -> 4677.6632 | J7: =Schedules!J122 -> 5106.9678 | K7: =Schedules!K122 -> 5532.3888 | L7: =Schedules!L122 -> 5920.0378
B8: Total Tax Shield | E8: Tax Rate | F8: =Assumptions!H53 -> 0.26 | H8: =H6-H7 -> -258.50649 | I8: =I6-I7 -> -279.6759 | J8: =J6-J7 -> -302.04997 | K8: =K6-K7 -> -323.19346 | L8: =L6-L7 -> -343.62507
B11: EBITDA METHOD
B12: EBITDA | H12: =Core_Model!H11 -> 15813.164 | I12: =Core_Model!I11 -> 17235.971 | J12: =Core_Model!J11 -> 18999.108 | K12: =Core_Model!K11 -> 20740.749 | L12: =Core_Model!L11 -> 22328.992
B13: Current Taxes | H13: =H6*-1 -> -4082.9898 | I13: =I6*-1 -> -4397.9873 | J13: =J6*-1 -> -4804.9179 | K13: =K6*-1 -> -5209.1954 | L13: =L6*-1 -> -5576.4128
B14: Capital Expenditure | H14: =Assumptions!H38*-1 -> -1458.0951 | I14: =Assumptions!I38*-1 -> -1577.6589 | J14: =Assumptions!J38*-1 -> -1703.8716 | K14: =Assumptions!K38*-1 -> -1823.1426 | L14: =Assumptions!L38*-1 -> -1932.5312
B15: Change in Working Capital | H15: =Schedules!H18*-1 -> -261.21941 | I15: =Schedules!I18*-1 -> -295.52825 | J15: =Schedules!J18*-1 -> -402.64418 | K15: =Schedules!K18*-1 -> -252.13479 | L15: =Schedules!L18*-1 -> -212.24962
B16: Unlevered Free Cash Flow | H16: =SUM(H12:H15) -> 10010.86 | I16: =SUM(I12:I15) -> 10964.796 | J16: =SUM(J12:J15) -> 12087.674 | K16: =SUM(K12:K15) -> 13456.276 | L16: =SUM(L12:L15) -> 14607.799
B19: NET INCOME METHOD
B20: Net Income | H20: =Core_Model!H25 -> 10788.312 | I20: =Core_Model!I25 -> 11882.65 | J20: =Core_Model!J25 -> 13214.816 | K20: =Core_Model!K25 -> 14510.565 | L20: =Core_Model!L25 -> 15674.603
B21: Other Income | H21: =Core_Model!H16*-1 -> -994.15575 | I21: =Core_Model!I16*-1 -> -1075.6765 | J21: =Core_Model!J16*-1 -> -1161.7306 | K21: =Core_Model!K16*-1 -> -1243.0518 | L21: =Core_Model!L16*-1 -> -1317.6349
B22: Depreciation 1 | H22: =Core_Model!H13*-1 -> 1354.0031 | I22: =Core_Model!I13*-1 -> 1456.1106 | J22: =Core_Model!J13*-1 -> 1566.591 | K22: =Core_Model!K13*-1 -> 1685.9097 | L22: =Core_Model!L13*-1 -> 1813.5807
B23: Deferred Tax 2 | H23: =Core_Model!H22*-1 -> 323.60796 | I23: =Core_Model!I22*-1 -> 295.22364 | J23: =Core_Model!J22*-1 -> 272.46344 | K23: =Core_Model!K22*-1 -> 254.93707 | L23: =Core_Model!L22*-1 -> 242.40582
B24: Interest Expense | H24: =Core_Model!H17*-1 -> -0.05 | I24: =Core_Model!I17*-1 -> 0 | J24: =Core_Model!J17*-1 -> 0 | K24: =Core_Model!K17*-1 -> 0 | L24: =Core_Model!L17*-1 -> -2
B25: Tax Shield From Interest | H25: =H8*-1 -> 258.50649 | I25: =I8*-1 -> 279.6759 | J25: =J8*-1 -> 302.04997 | K25: =K8*-1 -> 323.19346 | L25: =L8*-1 -> 343.62507
B26: Capital Expenditure | H26: =H14 -> -1458.0951 | I26: =I14 -> -1577.6589 | J26: =J14 -> -1703.8716 | K26: =K14 -> -1823.1426 | L26: =L14 -> -1932.5312
B27: Change in Working Capital | H27: =H15 -> -261.21941 | I27: =I15 -> -295.52825 | J27: =J15 -> -402.64418 | K27: =K15 -> -252.13479 | L27: =L15 -> -212.24962
B28: Unlevered Free Cash Flow | H28: =SUM(H20:H27) -> 10010.91 | I28: =SUM(I20:I27) -> 10964.796 | J28: =SUM(J20:J27) -> 12087.674 | K28: =SUM(K20:K27) -> 13456.276 | L28: =SUM(L20:L27) -> 14609.799
B30: Two UFCF Methods Different? | H30: =IF(ROUND(H16-H28,1)<10,0,1) -> 0 | I30: =IF(ROUND(I16-I28,1)<10,0,1) -> 0 | J30: =IF(ROUND(J16-J28,1)<10,0,1) -> 0 | K30: =IF(ROUND(K16-K28,1)<10,0,1) -> 0 | L30: =IF(ROUND(L16-L28,1)<10,0,1) -> 0
B32: Discounted Cash Flow: Perpetuity Method
B33: =B3 -> Particulars | C33: =C3 | D33: =D3 | H33: =H3 -> 2026 | I33: =I3 -> 2027 | J33: =J3 -> 2028 | K33: =K3 -> 2029 | L33: =L3 -> 2030
G35: Valuation | H35: Discrete Forecast | L35: Term
G36: (YY-MM-DD) | H36: (YY-MM-DD) | I36: (YY-MM-DD) | J36: (YY-MM-DD) | K36: (YY-MM-DD) | L36: (YY-MM-DD)
B37: Terminal Growth | C37: =Sensitivity_Analysis!H56 -> 0.02 | E37: Fiscal Year End | G37: =Assumptions!H58 -> 46201 | H37: =Assumptions!H59 -> 46387 | I37: =EDATE(H37,12) -> 46752 | J37: =EDATE(I37,12) -> 47118 | K37: =EDATE(J37,12) -> 47483 | L37: =EDATE(K37,12) -> 47848
B38: WACC | C38: =Sensitivity_Analysis!H57 -> 0.11 | E38: Cash Flow Timing | G38: =G37 -> 46201 | H38: =Assumptions!H60 -> 46203 | I38: =EDATE(H38,12) -> 46568 | J38: =EDATE(I38,12) -> 46934 | K38: =EDATE(J38,12) -> 47299 | L38: =EDATE(K38,12) -> 47664
B40: Unlevered Free Cash Flow | H40: =H28 -> 10010.91 | I40: =I28 -> 10964.796 | J40: =J28 -> 12087.674 | K40: =K28 -> 13456.276 | L40: =L28 -> 14609.799
B41: UNADJUSTED CASH FLOW
B42: Discrete Forecast | H42: =H40 -> 10010.91 | I42: =I40 -> 10964.796 | J42: =J40 -> 12087.674 | K42: =K40 -> 13456.276
B43: Terminal Value | H43: 0 | I43: 0 | J43: 0 | K43: =L40/(C38-C37) -> 162331.09
B44: Total Cash Flow | H44: =SUM(H42:H43) -> 10010.91 | I44: =SUM(I42:I43) -> 10964.796 | J44: =SUM(J42:J43) -> 12087.674 | K44: =SUM(K42:K43) -> 175787.37
B46: ADJUSTED CASH FLOW
B47: Partial Period Adjustment | H47: =YEARFRAC(H37,G37) -> 0.50833333 | I47: =YEARFRAC(I37,H37) -> 1 | J47: =YEARFRAC(J37,I37) -> 1 | K47: =YEARFRAC(K37,J37) -> 1
B49: Discrete Forecast | H49: =H42*H$47 -> 5088.8791 | I49: =I42*I$47 -> 10964.796 | J49: =J42*J$47 -> 12087.674 | K49: =K42*K$47 -> 13456.276
B50: Terminal Value | H50: =H43 -> 0 | I50: =I43 -> 0 | J50: =J43 -> 0 | K50: =K43*K47 -> 162331.09
B51: Total Cash Flow | G51: 0 | H51: =SUM(H49:H50) -> 5088.8791 | I51: =SUM(I49:I50) -> 10964.796 | J51: =SUM(J49:J50) -> 12087.674 | K51: =SUM(K49:K50) -> 175787.37
B53: DISCOUNTED CASH FLOW
B54: Years for Discounting | H54: =G54+YEARFRAC(H38,G38) -> 0.0055555556 | I54: =H54+YEARFRAC(I38,H38) -> 1.0055556 | J54: =I54+YEARFRAC(J38,I38) -> 2.0055556 | K54: =J54+YEARFRAC(K38,J38) -> 3.0055556
B56: Discrete Forecast | H56: =H49/(1+$C$38)^H$54 -> 5085.9295 | I56: =I49/(1+$C$38)^I$54 -> 9872.4695 | J56: =J49/(1+$C$38)^J$54 -> 9804.9413 | K56: =K49/(1+$C$38)^K$54 -> 9833.4105
B57: Terminal Value | H57: =H50/(1+$C$358)^I$376 -> 0 | I57: =I50/(1+$C$358)^J$376 -> 0 | J57: =J50/(1+$C$358)^K$376 -> 0 | K57: =K50/(1+$C$38)^K54 -> 118626.3
B58: Total Cash Flow | H58: =SUM(H56:H57) -> 5085.9295 | I58: =SUM(I56:I57) -> 9872.4695 | J58: =SUM(J56:J57) -> 9804.9413 | K58: =SUM(K56:K57) -> 128459.71
D61: ENTERPRISE VALUE | H61: ENTERPRISE VALUE
D62: Manual Method | F62: =SUM(H58:K58) -> 153223.05 | H62: PV of Discrete | J62: =K62/$K$64 -> 0.22579338 | K62: =SUM(H56:L56) -> 34596.751
D63: XNPV Function 1 | F63: =XNPV(C38,G51:K51,G38:K38) -> 153184.74 | H63: PV of Terminal | J63: =K63/$K$64 -> 0.77420662 | K63: =SUM(H57:L57) -> 118626.3
H64: Enterprise Value | J64: =K64/$K$64 -> 1 | K64: =SUM(K62:K63) -> 153223.05
D66: EQUITY VALUE | H66: EQUITY VALUE PER SHARE
D67: Enterprise Value | F67: =F63 -> 153184.74 | H67: Equity Value | K67: =F70 -> 164700.23
D68: Less: Net Debt | F68: =Assumptions!H63*-1 -> -1388.3175 | H68: Shares Outstanding | K68: =Assumptions!H57 -> 234.95913
D69: Add: CCE | F69: =Core_Model!L32+Core_Model!L33 -> 12903.804 | H69: Equity Value per Share | K69: =K67/K68 -> 700.97395
D70: Equity Value | F70: =SUM(F67:F69) -> 164700.23
B72: Discounted Cash Flow: Multiple Method
B73: =B33 -> Particulars | C73: =C33 | D73: =D33 | H73: =H33 -> 2026 | I73: =I33 -> 2027 | J73: =J33 -> 2028 | K73: =K33 -> 2029 | L73: =L33 -> 2030
G75: Valuation | H75: Discrete Forecast | L75: Term
G76: (YY-MM-DD) | H76: (YY-MM-DD) | I76: (YY-MM-DD) | J76: (YY-MM-DD) | K76: (YY-MM-DD) | L76: (YY-MM-DD)
B77: Terminal Multiple | C77: =Sensitivity_Analysis!H58 -> 7 | E77: Fiscal Year End | G77: =G37 -> 46201 | H77: =H37 -> 46387 | I77: =I37 -> 46752 | J77: =J37 -> 47118 | K77: =K37 -> 47483 | L77: =L37 -> 47848
B78: WACC | C78: =Sensitivity_Analysis!H57 -> 0.11 | E78: Cash Flow Timing | G78: =G38 -> 46201 | H78: =H38 -> 46203 | I78: =I38 -> 46568 | J78: =J38 -> 46934 | K78: =K38 -> 47299 | L78: =L38 -> 47664
B80: Unlevered Free Cash Flow | G80: 0 | H80: =H28 -> 10010.91 | I80: =I28 -> 10964.796 | J80: =J28 -> 12087.674 | K80: =K28 -> 13456.276 | L80: =L28 -> 14609.799
B81: EBITDA | L81: =L12 -> 22328.992
B83: UNADJUSTED CASH FLOW | E83: Terminal | H83: =H80 -> 10010.91 | I83: =I80 -> 10964.796 | J83: =J80 -> 12087.674 | K83: =K80 -> 13456.276 | L83: =L80 -> 14609.799
B84: Discrete Forecast | E84: Adjustment | H84: 0 | I84: 0 | J84: 0 | K84: 0 | L84: =(L81*C77)/(1+C78)^E85 -> 148356.19
B85: Terminal Value 1 | E85: =YEARFRAC(L77,L78) -> 0.5 | H85: =SUM(H83:H84) -> 10010.91 | I85: =SUM(I83:I84) -> 10964.796 | J85: =SUM(J83:J84) -> 12087.674 | K85: =SUM(K83:K84) -> 13456.276 | L85: =SUM(L83:L84) -> 162965.99
B86: Total Cash Flow
B88: ADJUSTED CASH FLOW | H88: =YEARFRAC(H77,G77) -> 0.50833333 | I88: =YEARFRAC(I77,H77) -> 1 | J88: =YEARFRAC(J77,I77) -> 1 | K88: =YEARFRAC(K77,J77) -> 1 | L88: =YEARFRAC(L77,K77) -> 1
B89: Partial Period Adjustment
B90: Discrete Forecast | H90: =H83*H88 -> 5088.8791 | I90: =I83*I88 -> 10964.796 | J90: =J83*J88 -> 12087.674 | K90: =K83*K88 -> 13456.276 | L90: =L83*L88 -> 14609.799
B91: Terminal Value | H91: =H84 -> 0 | I91: =I84 -> 0 | J91: =J84 -> 0 | K91: =K84 -> 0 | L91: =L88*L84 -> 148356.19
B92: Total Cash Flow | G92: 0 | H92: =SUM(H90:H91) -> 5088.8791 | I92: =SUM(I90:I91) -> 10964.796 | J92: =SUM(J90:J91) -> 12087.674 | K92: =SUM(K90:K91) -> 13456.276 | L92: =SUM(L90:L91) -> 162965.99
B94: DISCOUNTED CASH FLOW
B95: Years for Discounting | H95: =G95+YEARFRAC(G78,H78) -> 0.0055555556 | I95: =H95+YEARFRAC(H78,I78) -> 1.0055556 | J95: =I95+YEARFRAC(I78,J78) -> 2.0055556 | K95: =J95+YEARFRAC(J78,K78) -> 3.0055556 | L95: =K95+YEARFRAC(K78,L78) -> 4.0055556
B96: Discrete Forecast | H96: =H90/(1+$C$78)^H95 -> 5085.9295 | I96: =I90/(1+$C$78)^I95 -> 9872.4695 | J96: =J90/(1+$C$78)^J95 -> 9804.9413 | K96: =K90/(1+$C$78)^K95 -> 9833.4105 | L96: =L90/(1+$C$78)^L95 -> 9618.3487
B97: Terminal Value | H97: =H91/(1+$C$78)^H95 -> 0 | I97: =I91/(1+$C$78)^I95 -> 0 | J97: =J91/(1+$C$78)^J95 -> 0 | K97: =K91/(1+$C$78)^K95 -> 0 | L97: =L91/(1+$C$78)^L95 -> 97670.174
B98: Total Cash Flow | H98: =SUM(H96:H97) -> 5085.9295 | I98: =SUM(I96:I97) -> 9872.4695 | J98: =SUM(J96:J97) -> 9804.9413 | K98: =SUM(K96:K97) -> 9833.4105 | L98: =SUM(L96:L97) -> 107288.52
D100: ENTERPRISE VALUE | H100: ENTERPRISE VALUE
D101: Manual Method | F101: =SUM(H98:L98) -> 141885.27 | H101: PV of Discrete | J101: =K101/$K$103 -> 0.31162571 | K101: =SUM(H96:L96) -> 44215.1
D102: XNPV Function 2 | F102: =XNPV(C78,G92:L92,G78:L78) -> 141850.11 | H102: PV of Terminal | J102: =K102/$K$103 -> 0.68837429 | K102: =SUM(H97:L97) -> 97670.174
H103: Enterprise Value | J103: =K103/$K$103 -> 1 | K103: =SUM(K101:K102) -> 141885.27
D106: EQUITY VALUE | H106: EQUITY VALUE PER SHARE
D107: Enterprise Value | F107: =F102 -> 141850.11 | H107: Equity Value | K107: =F110 -> 153365.6
D108: Less: Net Debt | F108: =Assumptions!H63*-1 -> -1388.3175 | H108: Shares Outstanding | K108: =Assumptions!H57 -> 234.95913
D109: Add: CCE | F109: =Core_Model!L32+Core_Model!L33 -> 12903.804 | H109: Equity Value | K109: =K107/K108 -> 652.73311
D110: Equity Value | F110: =SUM(F107:F109) -> 153365.6

Sheet Sensitivity_Analysis
B2: Dashboard: Perpetuity Method
B5: Driver Switch
B8: Enterprise Value | J8: Equity Value
D10: Terminal Growth Rate | L10: Terminal Growth Rate
C11: =Valuation_DCF!F63 -> 153184.74 | D11: =E11-0.005 -> 0.01 | E11: =F11-0.005 -> 0.015 | F11: =Assumptions!H61 -> 0.02 | G11: =F11+0.005 -> 0.025 | H11: =G11+0.005 -> 0.03 | L11: =D11 -> 0.01 | M11: =E11 -> 0.015 | N11: =F11 -> 0.02 | O11: =G11 -> 0.025 | P11: =H11 -> 0.03
B12: WACC | C12: =C13-0.01 -> 0.09 | D12: 176609.49 | E12: 186004.04 | F12: 196740.67 | G12: 209129.08 | H12: 223582.23 | J12: WACC | K12: =C12 -> 0.09 | L12: =D12-$H$59+$H$60 -> 188124.98 | M12: =E12-$H$59+$H$60 -> 197519.53 | N12: =F12-$H$59+$H$60 -> 208256.15 | O12: =G12-$H$59+$H$60 -> 220644.57 | P12: =H12-$H$59+$H$60 -> 235097.72
C13: =C14-0.01 -> 0.1 | D13: 156999.24 | E13: 164167.84 | F13: 172232.52 | G13: 181372.49 | H13: 191818.17 | K13: =C13 -> 0.1 | L13: =D13-$H$59+$H$60 -> 168514.72 | M13: =E13-$H$59+$H$60 -> 175683.33 | N13: =F13-$H$59+$H$60 -> 183748.01 | O13: =G13-$H$59+$H$60 -> 192887.97 | P13: =H13-$H$59+$H$60 -> 203333.65
C14: =Assumptions!H43 -> 0.11 | D14: 141325.41 | E14: 146942.99 | F14: 153184.74 | G14: 160160.82 | H14: 168008.91 | K14: =C14 -> 0.11 | L14: =D14-$H$59+$H$60 -> 152840.89 | M14: =E14-$H$59+$H$60 -> 158458.47 | N14: =F14-$H$59+$H$60 -> 164700.23 | O14: =G14-$H$59+$H$60 -> 171676.31 | P14: =H14-$H$59+$H$60 -> 179524.39
C15: =C14+0.01 -> 0.12 | D15: 128513.92 | E15: 133011.45 | F15: 137958.72 | G15: 143426.77 | H15: 149502.37 | K15: =C15 -> 0.12 | L15: =D15-$H$59+$H$60 -> 140029.41 | M15: =E15-$H$59+$H$60 -> 144526.93 | N15: =F15-$H$59+$H$60 -> 149474.21 | O15: =G15-$H$59+$H$60 -> 154942.25 | P15: =H15-$H$59+$H$60 -> 161017.86
C16: =C15+0.01 -> 0.13 | D16: 117848.74 | E16: 121513.65 | F16: 125511.74 | G16: 129890.59 | H16: 134707.34 | K16: =C16 -> 0.13 | L16: =D16-$H$59+$H$60 -> 129364.23 | M16: =E16-$H$59+$H$60 -> 133029.14 | N16: =F16-$H$59+$H$60 -> 137027.23 | O16: =G16-$H$59+$H$60 -> 141406.08 | P16: =H16-$H$59+$H$60 -> 146222.82
B19: Equity Value per Share | K19: Premium (Discount) to Stock Price
D21: Terminal Growth Rate | L21: Terminal Growth Rate
D22: =L11 -> 0.01 | E22: =M11 -> 0.015 | F22: =N11 -> 0.02 | G22: =O11 -> 0.025 | H22: =P11 -> 0.03 | L22: =D22 -> 0.01 | M22: =E22 -> 0.015 | N22: =F22 -> 0.02 | O22: =G22 -> 0.025 | P22: =H22 -> 0.03
B23: WACC | C23: =K12 -> 0.09 | D23: =L12/$H$61 -> 800.6711 | E23: =M12/$H$61 -> 840.65485 | F23: =N12/$H$61 -> 886.35057 | G23: =O12/$H$61 -> 939.07639 | H23: =P12/$H$61 -> 1000.5899 | J23: WACC | K23: =C23 -> 0.09 | L23: =$H$62/D23 -> 2.747695 | M23: =$H$62/E23 -> 2.6170074 | N23: =$H$62/F23 -> 2.4820879 | O23: =$H$62/G23 -> 2.3427274 | P23: =$H$62/H23 -> 2.1987031
C24: =K13 -> 0.1 | D24: =L13/$H$61 -> 717.20868 | E24: =M13/$H$61 -> 747.71868 | F24: =N13/$H$61 -> 782.04243 | G24: =O13/$H$61 -> 820.94268 | H24: =P13/$H$61 -> 865.40011 | K24: =C24 -> 0.1 | L24: =$H$62/D24 -> 3.0674475 | M24: =$H$62/E24 -> 2.9422831 | N24: =$H$62/F24 -> 2.8131466 | O24: =$H$62/G24 -> 2.6798461 | P24: =$H$62/H24 -> 2.5421767
C25: =K14 -> 0.11 | D25: =L14/$H$61 -> 650.49993 | E25: =M14/$H$61 -> 674.40868 | F25: =N14/$H$61 -> 700.97395 | G25: =O14/$H$61 -> 730.66456 | H25: =P14/$H$61 -> 764.06648 | K25: =C25 -> 0.11 | L25: =$H$62/D25 -> 3.3820142 | M25: =$H$62/E25 -> 3.262117 | N25: =$H$62/F25 -> 3.1384904 | O25: =$H$62/G25 -> 3.0109576 | P25: =$H$62/H25 -> 2.8793306
C26: =K15 -> 0.12 | D26: =L15/$H$61 -> 595.97347 | E26: =M15/$H$61 -> 615.11521 | F26: =N15/$H$61 -> 636.17112 | G26: =O15/$H$61 -> 659.44344 | H26: =P15/$H$61 -> 685.30158 | K26: =C26 -> 0.12 | L26: =$H$62/D26 -> 3.6914395 | M26: =$H$62/E26 -> 3.5765658 | N26: =$H$62/F26 -> 3.4581891 | O26: =$H$62/G26 -> 3.3361466 | P26: =$H$62/H26 -> 3.2102655
C27: =K16 -> 0.13 | D27: =L16/$H$61 -> 550.58184 | E27: =M16/$H$61 -> 566.17992 | F27: =N16/$H$61 -> 583.19601 | G27: =O16/$H$61 -> 601.83268 | H27: =P16/$H$61 -> 622.33302 | K27: =C27 -> 0.13 | L27: =$H$62/D27 -> 3.9957729 | M27: =$H$62/E27 -> 3.8856906 | N27: =$H$62/F27 -> 3.7723166 | O27: =$H$62/G27 -> 3.6555011 | P27: =$H$62/H27 -> 3.5350848
B30: Dashboard: Multiple Method
B32: Enterprise Value | J32: Equity Value
D34: Terminal Multiple | L34: Terminal Multiple
C35: =Valuation_DCF!F102 -> 141850.11 | D35: =E35-0.5 -> 6 | E35: =F35-0.5 -> 6.5 | F35: =Assumptions!H62 -> 7 | G35: =+F35+0.5 -> 7.5 | H35: =+G35+0.5 -> 8 | L35: =D35 -> 6 | M35: =E35 -> 6.5 | N35: =F35 -> 7 | O35: =G35 -> 7.5 | P35: =H35 -> 8
B36: WACC | C36: =C37-0.01 -> 0.09 | D36: 136877.33 | E36: 144447.62 | F36: 152017.9 | G36: 159588.19 | H36: 167158.47 | J36: WACC | K36: =C36 -> 0.09 | L36: =D36-$H$59+$H$60 -> 148392.82 | M36: =E36-$H$59+$H$60 -> 155963.1 | N36: =F36-$H$59+$H$60 -> 163533.39 | O36: =G36-$H$59+$H$60 -> 171103.67 | P36: =H36-$H$59+$H$60 -> 178673.96
C37: =C38-0.01 -> 0.1 | D37: 132283.1 | E37: 139548.04 | F37: 146812.98 | G37: 154077.91 | H37: 161342.85 | K37: =C37 -> 0.1 | L37: =D37-$H$59+$H$60 -> 143798.59 | M37: =E37-$H$59+$H$60 -> 151063.52 | N37: =F37-$H$59+$H$60 -> 158328.46 | O37: =G37-$H$59+$H$60 -> 165593.4 | P37: =H37-$H$59+$H$60 -> 172858.33
C38: =Assumptions!H43 -> 0.11 | D38: 127901.11 | E38: 134875.61 | F38: 141850.11 | G38: 148824.62 | H38: 155799.12 | K38: =C38 -> 0.11 | L38: =D38-$H$59+$H$60 -> 139416.6 | M38: =E38-$H$59+$H$60 -> 146391.1 | N38: =F38-$H$59+$H$60 -> 153365.6 | O38: =G38-$H$59+$H$60 -> 160340.1 | P38: =H38-$H$59+$H$60 -> 167314.6
C39: =C38+0.01 -> 0.12 | D39: 123719.57 | E39: 130417.7 | F39: 137115.83 | G39: 143813.96 | H39: 150512.09 | K39: =C39 -> 0.12 | L39: =D39-$H$59+$H$60 -> 135235.06 | M39: =E39-$H$59+$H$60 -> 141933.19 | N39: =F39-$H$59+$H$60 -> 148631.32 | O39: =G39-$H$59+$H$60 -> 155329.45 | P39: =H39-$H$59+$H$60 -> 162027.57
C40: =C39+0.01 -> 0.13 | D40: 119727.47 | E40: 126162.48 | F40: 132597.5 | G40: 139032.52 | H40: 145467.54 | K40: =C40 -> 0.13 | L40: =D40-$H$59+$H$60 -> 131242.95 | M40: =E40-$H$59+$H$60 -> 137677.97 | N40: =F40-$H$59+$H$60 -> 144112.99 | O40: =G40-$H$59+$H$60 -> 150548.01 | P40: =H40-$H$59+$H$60 -> 156983.03
C43: Equity Value per Share | J43: Premium (Discount) to Stock Price
D45: Terminal Multiple | L45: Terminal Multiple
D46: =D35 -> 6 | E46: =E35 -> 6.5 | F46: =F35 -> 7 | G46: =G35 -> 7.5 | H46: =H35 -> 8 | L46: =L35 -> 6 | M46: =M35 -> 6.5 | N46: =N35 -> 7 | O46: =O35 -> 7.5 | P46: =P35 -> 8
B47: WACC | C47: =C36 -> 0.09 | D47: =L36/$H$61 -> 631.56864 | E47: =M36/$H$61 -> 663.78823 | F47: =N36/$H$61 -> 696.00781 | G47: =O36/$H$61 -> 728.2274 | H47: =P36/$H$61 -> 760.44698 | J47: WACC | K47: =K36 -> 0.09 | L47: =$H$62/D47 -> 3.4833902 | M47: =$H$62/E47 -> 3.3143101 | N47: =$H$62/F47 -> 3.1608841 | O47: =$H$62/G47 -> 3.0210344 | P47: =$H$62/H47 -> 2.8930353
C48: =C37 -> 0.1 | D48: =L37/$H$61 -> 612.01533 | E48: =M37/$H$61 -> 642.93534 | F48: =N37/$H$61 -> 673.85534 | G48: =O37/$H$61 -> 704.77534 | H48: =P37/$H$61 -> 735.69534 | K48: =K37 -> 0.1 | L48: =$H$62/D48 -> 3.5946812 | M48: =$H$62/E48 -> 3.421806 | N48: =$H$62/F48 -> 3.2647957 | O48: =$H$62/G48 -> 3.1215621 | P48: =$H$62/H48 -> 2.9903683
C49: =C38 -> 0.11 | D49: =L38/$H$61 -> 593.36532 | E49: =M38/$H$61 -> 623.04921 | F49: =N38/$H$61 -> 652.73311 | G49: =O38/$H$61 -> 682.417 | H49: =P38/$H$61 -> 712.1009 | K49: =K38 -> 0.11 | L49: =$H$62/D49 -> 3.7076653 | M49: =$H$62/E49 -> 3.5310212 | N49: =$H$62/F49 -> 3.3704434 | O49: =$H$62/G49 -> 3.2238353 | P49: =$H$62/H49 -> 3.0894498
C50: =C39 -> 0.12 | D50: =L39/$H$61 -> 575.56845 | E50: =M39/$H$61 -> 604.07608 | F50: =N39/$H$61 -> 632.58372 | G50: =O39/$H$61 -> 661.09135 | H50: =P39/$H$61 -> 689.59898 | K50: =K39 -> 0.12 | L50: =$H$62/D50 -> 3.8223082 | M50: =$H$62/E50 -> 3.6419254 | N50: =$H$62/F50 -> 3.4778006 | O50: =$H$62/G50 -> 3.3278306 | P50: =$H$62/H50 -> 3.1902599
C51: =C40 -> 0.13 | D51: =L40/$H$61 -> 558.5778 | E51: =M40/$H$61 -> 585.96562 | F51: =N40/$H$61 -> 613.35345 | G51: =O40/$H$61 -> 640.74127 | H51: =P40/$H$61 -> 668.1291 | K51: =K40 -> 0.13 | L51: =$H$62/D51 -> 3.938574 | M51: =$H$62/E51 -> 3.7544865 | N51: =$H$62/F51 -> 3.5868389 | O51: =$H$62/G51 -> 3.4335232 | P51: =$H$62/H51 -> 3.2927768
B54: Selected Inputs
B56: Terminal Growth Rate | H56: =Assumptions!H61 -> 0.02
B57: WACC | H57: =Assumptions!H43 -> 0.11
B58: Terminal Multiple | H58: =Assumptions!H62 -> 7
B59: Net Debt | H59: =Assumptions!H63 -> 1388.3175
B60: CCE | H60: =Core_Model!L32+Core_Model!L33 -> 12903.804
B61: Shares Outstanding | H61: =Assumptions!H57 -> 234.95913
B62: Current Stock Price | H62: 2200

Sheet Appendix
B2: Ref. No | C2: Note | D2: Calc & Misc
B3: 1 | C3: pg 107
B4: 2 | C4: - | D4: =8625/1355 -> 6.3653137
B5: 3 | C5: pg 381 | D5: =(12004-465)/808 -> 14.280941
B6: 4 | C6: 2.8%, 2.2%, 1.8% of Revenue
B7: 5 | C7: 1.5% of Revenue
B8: 6 | C8: .5% of EBIT
B9: 7 | C9: 9.5% of Revenue
B10: 8 | C10: Amortize at 3%
B11: 9 | C11: business type and stage | D11: 85% of capex
B12: 10 | C12: 3.8% of Revenue
B13: 11 | C13: pg 375
B14: 12 | C14: 0.92% of Revenue
B15: 13 | C15: 5% of Lease Rate
B16: 14 | C16: LT Debt, RCL, Lease Liabilities, NCI

Sheet Rough
B2: Debt & Interest Schedule
B3: (All amounts in ₹ crores, unless otherwise stated)
B4: Particulars | C4: Units | E4: 2023 | F4: 2024 | G4: 2025 | H4: =Schedules!H26 -> 2026 | I4: =Schedules!I26 -> 2027 | J4: =Schedules!J26 -> 2028 | K4: =Schedules!K26 -> 2029 | L4: =Schedules!L26 -> 2030
B6: LONG TERM DEBT
B8: Beginning Balance | E8: =D10 -> 0 | F8: =E10 -> 0 | G8: =F10 -> 0
B9: Increase / (Decrease) | E9: 0 | F9: 0 | G9: 0
B10: Ending Balance | D10: 0 | E10: =SUM(E8:E9) -> 0 | F10: =SUM(F8:F9) -> 0 | G10: =SUM(G8:G9) -> 0
B12: AVAILABLE CASH
B14: Beginning Cash Balance
B15: Cash from Operations
B16: Cash from Investing
B17: Change in Long-Term Debt
B18: Change in Common Equity
B19: Dividends
B20: Cash Available for Revolving Credit Line
B23: REVOLVING CREDIT LINE
B25: Beginning Balance
B26: Increase / (Decrease)
B27: Ending Balance
B29: COMMON EQUITY
B31: Beginning Balance | E31: =D33 -> 235 | F31: =E33 -> 235 | G31: =F33 -> 235
B32: Increase / (Decrease) | E32: =Core_Model!E60-Core_Model!D60 -> 0 | F32: =Core_Model!F60-Core_Model!E60 -> 0 | G32: =Core_Model!G60-Core_Model!F60 -> 0
B33: Ending Balance | D33: 235 | E33: =SUM(E31:E32) -> 235 | F33: =SUM(F31:F32) -> 235 | G33: =SUM(G31:G32) -> 235
